{"items": [{"id": "RB_2242_13323F_50", "title": "Ray-Ban Wayfarer Oval RB 2242 13323F 50 Férfi, Női napszemüveg", "img": "https://eoptika.hu/img/43321/RB_2242_13323F_50/RB_2242_13323F_50.webp", "desc": "100% Ár-garancia, 5400+ átvételi pont, akár ingyenes szállítás", "price": 49190.0, "original_price": null, "currency": "HUF", "discount": null, "url": "https://www.dpbolvw.net/click-101579008-14005686?url=https%3A%2F%2Feoptika.hu%2Fray-ban-napszemuveg-rb-2242-13323f-50", "partner": "cj-eoptika", "category_path": "Apparel & Accessories > Clothing Accessories > Sunglasses", "findora_main": "latas", "cat": "latas"}, {"id": "RB_2242_13323F_53", "title": "Ray-Ban Wayfarer Oval RB 2242 13323F 53 Férfi, Női napszemüveg", "img": "https://eoptika.hu/img/43321/RB_2242_13323F_53/RB_2242_13323F_53.webp", "desc": "100% Ár-garancia, 5400+ átvételi pont, akár ingyenes szállítás", "price": 46700.0, "original_price": null, "currency": "HUF", "discount": null, "url": "https://www.kqzyfj.com/click-101579008-14005686?url=https%3A%2F%2Feoptika.hu%2Fray-ban-napszemuveg-rb-2242-13323f-53", "partner": "cj-eoptika", "category_path": "Apparel & Accessories > Clothing Accessories > Sunglasses", "findora_main": "latas", "cat": "latas"}, {"id": "RB_2242_133371_50", "title": "Ray-Ban Wayfarer Oval RB 2242 133371 50 Férfi, Női napszemüveg", "img": "https://eoptika.hu/img/43321/RB_2242_133371_50/RB_2242_133371_50.webp", "desc": "100% Ár-garancia, 5400+ átvételi pont, akár ingyenes szállítás", "price": 49190.0, "original_price": null, "currency": "HUF", "discount": null, "url": "https://www.jdoqocy.com/click-101579008-14005686?url=https%3A%2F%2Feoptika.hu%2Fray-ban-napszemuveg-rb-2242-133371-50", "partner": "cj-eoptika", "category_path": "Apparel & Accessories > Clothing Accessories > Sunglasses", "findora_main": "latas", "cat": "latas"}, {"id": "RB_2242_133371_53", "title": "Ray-Ban Wayfarer Oval RB 2242 133371 53 Férfi, Női napszemüveg", "img": "https://eoptika.hu/img/43321/RB_2242_133371_53/RB_2242_133371_53.webp", "desc": "100% Ár-garancia, 5400+ átvételi pont, akár ingyenes szállítás", "price": 49190.0, "original_price": null, "currency": "HUF", "discount": null, "url": "https://www.tkqlhce.com/click-101579008-14005686?url=https%3A%2F%2Feoptika.hu%2Fray-ban-napszemuveg-rb-2242-133371-53", "partner": "cj-eoptika", "category_path": "Apparel & Accessories > Clothing Accessories > Sunglasses", "findora_main": "latas", "cat": "latas"}, {"id": "RB_2242_133451_50", "title": "Ray-Ban Wayfarer Oval RB 2242 133451 50 Férfi, Női napszemüveg", "img": "https://eoptika.hu/img/43321/RB_2242_133451_50/RB_2242_133451_50.webp", "desc": "100% Ár-garancia, 5400+ átvételi pont, akár ingyenes szállítás", "price": 49190.0, "original_price": null, "currency": "HUF", "discount": null, "url": "https://www.dpbolvw.net/click-101579008-14005686?url=https%3A%2F%2Feoptika.hu%2Fray-ban-napszemuveg-rb-2242-133451-50", "partner": "cj-eoptika", "category_path": "Apparel & Accessories > Clothing Accessories > Sunglasses", "findora_main": "latas", "cat": "latas"}, {"id": "RB_2242_133451_53", "title": "Ray-Ban Wayfarer Oval RB 2242 133451 53 Férfi, Női napszemüveg", "img": "https://eoptika.hu/img/43321/RB_2242_133451_53/RB_2242_133451_53.webp", "desc": "100% Ár-garancia, 5400+ átvételi pont, akár ingyenes szállítás", "price": 46700.0, "original_price": null, "currency": "HUF", "discount": null, "url": "https://www.tkqlhce.com/click-101579008-14005686?url=https%3A%2F%2Feoptika.hu%2Fray-ban-napszemuveg-rb-2242-133451-53", "partner": "cj-eoptika", "category_path": "Apparel & Accessories > Clothing Accessories > Sunglasses", "findora_main": "latas", "cat": "latas"}, {"id": "RB_2242_90131_50", "title": "Ray-Ban Wayfarer Oval RB 2242 901/31 50 Férfi, Női napszemüveg", "img": "https://eoptika.hu/img/43321/RB_2242_90131_50/RB_2242_90131_50.webp", "desc": "100% Ár-garancia, 5400+ átvételi pont, akár ingyenes szállítás", "price": 46390.0, "original_price": null, "currency": "HUF", "discount": null, "url": "https://www.jdoqocy.com/click-101579008-14005686?url=https%3A%2F%2Feoptika.hu%2Fray-ban-napszemuveg-rb-2242-90131-50", "partner": "cj-eoptika", "category_path": "Apparel & Accessories > Clothing Accessories > Sunglasses", "findora_main": "latas", "cat": "latas"}, {"id": "RB_2242_90131_53", "title": "Ray-Ban Wayfarer Oval RB 2242 901/31 53 Férfi, Női napszemüveg", "img": "https://eoptika.hu/img/43321/RB_2242_90131_53/RB_2242_90131_53.webp", "desc": "100% Ár-garancia, 5400+ átvételi pont, akár ingyenes szállítás", "price": 44100.0, "original_price": null, "currency": "HUF", "discount": null, "url": "https://www.dpbolvw.net/click-101579008-14005686?url=https%3A%2F%2Feoptika.hu%2Fray-ban-napszemuveg-rb-2242-90131-53", "partner": "cj-eoptika", "category_path": "Apparel & Accessories > Clothing Accessories > Sunglasses", "findora_main": "latas", "cat": "latas"}, {"id": "RB_2242_902R5_50", "title": "Ray-Ban Wayfarer Oval RB 2242 902/R5 50 Férfi, Női napszemüveg", "img": "https://eoptika.hu/img/43321/RB_2242_902R5_50/RB_2242_902R5_50.webp", "desc": "100% Ár-garancia, 5400+ átvételi pont, akár ingyenes szállítás", "price": 46390.0, "original_price": null, "currency": "HUF", "discount": null, "url": "https://www.anrdoezrs.net/click-101579008-14005686?url=https%3A%2F%2Feoptika.hu%2Fray-ban-napszemuveg-rb-2242-902r5-50", "partner": "cj-eoptika", "category_path": "Apparel & Accessories > Clothing Accessories > Sunglasses", "findora_main": "latas", "cat": "latas"}, {"id": "TH_2161_807_49", "title": "Tommy Hilfiger TH 2161 807 49 Női szemüvegkeret (optikai keret)", "img": "https://eoptika.hu/img/43321/TH_2161_807_49/TH_2161_807_49.webp", "desc": "100% Ár-garancia, 5400+ átvételi pont, akár ingyenes szállítás", "price": 49690.0, "original_price": null, "currency": "HUF", "discount": null, "url": "https://www.jdoqocy.com/click-101579008-14005686?url=https%3A%2F%2Feoptika.hu%2Ftommy-hilfiger-szemuvegkeret-th-2161-807-49", "partner": "cj-eoptika", "category_path": "Health & Beauty > Personal Care > Vision Care > Eyeglasses", "findora_main": "latas", "cat": "latas"}, {"id": "TH_2161_KB7_49", "title": "Tommy Hilfiger TH 2161 KB7 49 Női szemüvegkeret (optikai keret)", "img": "https://eoptika.hu/img/43321/TH_2161_KB7_49/TH_2161_KB7_49.webp", "desc": "100% Ár-garancia, 5400+ átvételi pont, akár ingyenes szállítás", "price": 49690.0, "original_price": null, "currency": "HUF", "discount": null, "url": "https://www.jdoqocy.com/click-101579008-14005686?url=https%3A%2F%2Feoptika.hu%2Ftommy-hilfiger-szemuvegkeret-th-2161-kb7-49", "partner": "cj-eoptika", "category_path": "Health & Beauty > Personal Care > Vision Care > Eyeglasses", "findora_main": "latas", "cat": "latas"}, {"id": "TH_2162_086_51", "title": "Tommy Hilfiger TH 2162 086 51 Női szemüvegkeret (optikai keret)", "img": "https://eoptika.hu/img/43321/TH_2162_086_51/TH_2162_086_51.webp", "desc": "100% Ár-garancia, 5400+ átvételi pont, akár ingyenes szállítás", "price": 58390.0, "original_price": null, "currency": "HUF", "discount": null, "url": "https://www.tkqlhce.com/click-101579008-14005686?url=https%3A%2F%2Feoptika.hu%2Ftommy-hilfiger-szemuvegkeret-th-2162-086-51", "partner": "cj-eoptika", "category_path": "Health & Beauty > Personal Care > Vision Care > Eyeglasses", "findora_main": "latas", "cat": "latas"}, {"id": "TH_2162_807_51", "title": "Tommy Hilfiger TH 2162 807 51 Női szemüvegkeret (optikai keret)", "img": "https://eoptika.hu/img/43321/TH_2162_807_51/TH_2162_807_51.webp", "desc": "100% Ár-garancia, 5400+ átvételi pont, akár ingyenes szállítás", "price": 58390.0, "original_price": null, "currency": "HUF", "discount": null, "url": "https://www.dpbolvw.net/click-101579008-14005686?url=https%3A%2F%2Feoptika.hu%2Ftommy-hilfiger-szemuvegkeret-th-2162-807-51", "partner": "cj-eoptika", "category_path": "Health & Beauty > Personal Care > Vision Care > Eyeglasses", "findora_main": "latas", "cat": "latas"}, {"id": "TH_2162_807_52", "title": "Tommy Hilfiger TH 2162 807 51 Női szemüvegkeret (optikai keret)", "img": "https://eoptika.hu/img/43321/TH_2162_807_52/TH_2162_807_52.webp", "desc": "100% Ár-garancia, 5400+ átvételi pont, akár ingyenes szállítás", "price": 48290.0, "original_price": null, "currency": "HUF", "discount": null, "url": "https://www.jdoqocy.com/click-101579008-14005686?url=https%3A%2F%2Feoptika.hu%2Fspd%2FTH_2162_807_52%2FTommy-Hilfiger-TH-2162-807-51-Noi-szemuvegkeret-op", "partner": "cj-eoptika", "category_path": "Health & Beauty > Personal Care > Vision Care > Eyeglasses", "findora_main": "latas", "cat": "latas"}, {"id": "TH_2162_9N4_51", "title": "Tommy Hilfiger TH 2162 9N4 51 Női szemüvegkeret (optikai keret)", "img": "https://eoptika.hu/img/43321/TH_2162_9N4_51/TH_2162_9N4_51.webp", "desc": "100% Ár-garancia, 5400+ átvételi pont, akár ingyenes szállítás", "price": 58390.0, "original_price": null, "currency": "HUF", "discount": null, "url": "https://www.tkqlhce.com/click-101579008-14005686?url=https%3A%2F%2Feoptika.hu%2Ftommy-hilfiger-szemuvegkeret-th-2162-9n4-51", "partner": "cj-eoptika", "category_path": "Health & Beauty > Personal Care > Vision Care > Eyeglasses", "findora_main": "latas", "cat": "latas"}, {"id": "TH_2167F_PJP_53", "title": "Tommy Hilfiger TH 2167/F PJP 53 Férfi szemüvegkeret (optikai keret)", "img": "https://eoptika.hu/img/43321/TH_2167F_PJP_53/TH_2167F_PJP_53.webp", "desc": "100% Ár-garancia, 5400+ átvételi pont, akár ingyenes szállítás", "price": 54690.0, "original_price": null, "currency": "HUF", "discount": null, "url": "https://www.dpbolvw.net/click-101579008-14005686?url=https%3A%2F%2Feoptika.hu%2Ftommy-hilfiger-szemuvegkeret-th-2167f-pjp-53", "partner": "cj-eoptika", "category_path": "Health & Beauty > Personal Care > Vision Care > Eyeglasses", "findora_main": "latas", "cat": "latas"}, {"id": "TH_2184S_08670_52", "title": "Tommy Hilfiger TH 2184/S 086/70 52 Férfi napszemüveg", "img": "https://eoptika.hu/img/43321/TH_2184S_08670_52/TH_2184S_08670_52.webp", "desc": "100% Ár-garancia, 5400+ átvételi pont, akár ingyenes szállítás", "price": 50690.0, "original_price": null, "currency": "HUF", "discount": null, "url": "https://www.dpbolvw.net/click-101579008-14005686?url=https%3A%2F%2Feoptika.hu%2Ftommy-hilfiger-napszemuveg-th-2184s-08670-52", "partner": "cj-eoptika", "category_path": "Apparel & Accessories > Clothing Accessories > Sunglasses", "findora_main": "latas", "cat": "latas"}, {"id": "TH_2184S_1ED70_52", "title": "Tommy Hilfiger TH 2184/S 1ED/70 52 Férfi napszemüveg", "img": "https://eoptika.hu/img/43321/TH_2184S_1ED70_52/TH_2184S_1ED70_52.webp", "desc": "100% Ár-garancia, 5400+ átvételi pont, akár ingyenes szállítás", "price": 50690.0, "original_price": null, "currency": "HUF", "discount": null, "url": "https://www.anrdoezrs.net/click-101579008-14005686?url=https%3A%2F%2Feoptika.hu%2Ftommy-hilfiger-napszemuveg-th-2184s-1ed70-52", "partner": "cj-eoptika", "category_path": "Apparel & Accessories > Clothing Accessories > Sunglasses", "findora_main": "latas", "cat": "latas"}, {"id": "TH_2184S_807IR_52", "title": "Tommy Hilfiger TH 2184/S 807IR 52 Férfi napszemüveg", "img": "https://eoptika.hu/img/43321/TH_2184S_807IR_52/TH_2184S_807IR_52.webp", "desc": "100% Ár-garancia, 5400+ átvételi pont, akár ingyenes szállítás", "price": 55290.0, "original_price": null, "currency": "HUF", "discount": null, "url": "https://www.jdoqocy.com/click-101579008-14005686?url=https%3A%2F%2Feoptika.hu%2Ftommy-hilfiger-napszemuveg-th-2184s-807ir-52", "partner": "cj-eoptika", "category_path": "Apparel & Accessories > Clothing Accessories > Sunglasses", "findora_main": "latas", "cat": "latas"}, {"id": "TH_2184S_PJP08_52", "title": "Tommy Hilfiger TH 2184/S PJP/08 52 Férfi napszemüveg", "img": "https://eoptika.hu/img/43321/TH_2184S_PJP08_52/TH_2184S_PJP08_52.webp", "desc": "100% Ár-garancia, 5400+ átvételi pont, akár ingyenes szállítás", "price": 50690.0, "original_price": null, "currency": "HUF", "discount": null, "url": "https://www.dpbolvw.net/click-101579008-14005686?url=https%3A%2F%2Feoptika.hu%2Ftommy-hilfiger-napszemuveg-th-2184s-pjp08-52", "partner": "cj-eoptika", "category_path": "Apparel & Accessories > Clothing Accessories > Sunglasses", "findora_main": "latas", "cat": "latas"}]}