{"items": [{"id": "7226_13181", "title": "Nemesacél gyűrű - hatalmas oroszlánfej - Nagyság: 68", "img": "https://ekszer-eshop.hu/7226-62801/nemesacel-gyuru-hatalmas-oroszlanfej.webp", "desc": "Patinás gyűrű sebészeti acélból oroszlánfej mintázatban.", "price": 4895, "discount": null, "url": "https://ekszer-eshop.hu/7226-nemesacel-gyuru-hatalmas-oroszlanfej.html#pa7226_13181", "partner": "ekszereshop", "category_path": "", "findora_main": "divat", "cat": "divat"}, {"id": "7226_19821", "title": "Nemesacél gyűrű - hatalmas oroszlánfej - Nagyság: 69", "img": "https://ekszer-eshop.hu/7226-62801/nemesacel-gyuru-hatalmas-oroszlanfej.webp", "desc": "Patinás gyűrű sebészeti acélból oroszlánfej mintázatban.", "price": 4895, "discount": null, "url": "https://ekszer-eshop.hu/7226-nemesacel-gyuru-hatalmas-oroszlanfej.html#pa7226_19821", "partner": "ekszereshop", "category_path": "", "findora_main": "divat", "cat": "divat"}, {"id": "7226_19822", "title": "Nemesacél gyűrű - hatalmas oroszlánfej - Nagyság: 70", "img": "https://ekszer-eshop.hu/7226-62801/nemesacel-gyuru-hatalmas-oroszlanfej.webp", "desc": "Patinás gyűrű sebészeti acélból oroszlánfej mintázatban.", "price": 4895, "discount": null, "url": "https://ekszer-eshop.hu/7226-nemesacel-gyuru-hatalmas-oroszlanfej.html#pa7226_19822", "partner": "ekszereshop", "category_path": "", "findora_main": "divat", "cat": "divat"}, {"id": "7226_54217", "title": "Nemesacél gyűrű - hatalmas oroszlánfej - Nagyság: 72", "img": "https://ekszer-eshop.hu/7226-62801/nemesacel-gyuru-hatalmas-oroszlanfej.webp", "desc": "Patinás gyűrű sebészeti acélból oroszlánfej mintázatban.", "price": 4895, "discount": null, "url": "https://ekszer-eshop.hu/7226-nemesacel-gyuru-hatalmas-oroszlanfej.html#pa7226_54217", "partner": "ekszereshop", "category_path": "", "findora_main": "divat", "cat": "divat"}, {"id": "7228_28144", "title": "Gyűrű nemesacélból - kártya szimbólum és koponya - Nagyság: 51", "img": "https://ekszer-eshop.hu/7228-9203/gyuru-nemesacelbol-kartya-szimbolum-es-koponya.webp", "desc": "Patinás gyűrű sebészeti acélból, kártya szimbólum és koponya mintázatban.", "price": 4140, "discount": null, "url": "https://ekszer-eshop.hu/7228-gyuru-nemesacelbol-kartya-szimbolum-es-koponya.html#pa7228_28144", "partner": "ekszereshop", "category_path": "", "findora_main": "divat", "cat": "divat"}, {"id": "7228_28145", "title": "Gyűrű nemesacélból - kártya szimbólum és koponya - Nagyság: 52", "img": "https://ekszer-eshop.hu/7228-9203/gyuru-nemesacelbol-kartya-szimbolum-es-koponya.webp", "desc": "Patinás gyűrű sebészeti acélból, kártya szimbólum és koponya mintázatban.", "price": 4140, "discount": null, "url": "https://ekszer-eshop.hu/7228-gyuru-nemesacelbol-kartya-szimbolum-es-koponya.html#pa7228_28145", "partner": "ekszereshop", "category_path": "", "findora_main": "divat", "cat": "divat"}, {"id": "7228_13186", "title": "Gyűrű nemesacélból - kártya szimbólum és koponya - Nagyság: 53", "img": "https://ekszer-eshop.hu/7228-9203/gyuru-nemesacelbol-kartya-szimbolum-es-koponya.webp", "desc": "Patinás gyűrű sebészeti acélból, kártya szimbólum és koponya mintázatban.", "price": 4140, "discount": null, "url": "https://ekszer-eshop.hu/7228-gyuru-nemesacelbol-kartya-szimbolum-es-koponya.html#pa7228_13186", "partner": "ekszereshop", "category_path": "", "findora_main": "divat", "cat": "divat"}, {"id": "7228_13188", "title": "Gyűrű nemesacélból - kártya szimbólum és koponya - Nagyság: 54", "img": "https://ekszer-eshop.hu/7228-9203/gyuru-nemesacelbol-kartya-szimbolum-es-koponya.webp", "desc": "Patinás gyűrű sebészeti acélból, kártya szimbólum és koponya mintázatban.", "price": 4140, "discount": null, "url": "https://ekszer-eshop.hu/7228-gyuru-nemesacelbol-kartya-szimbolum-es-koponya.html#pa7228_13188", "partner": "ekszereshop", "category_path": "", "findora_main": "divat", "cat": "divat"}, {"id": "7228_13191", "title": "Gyűrű nemesacélból - kártya szimbólum és koponya - Nagyság: 55", "img": "https://ekszer-eshop.hu/7228-9203/gyuru-nemesacelbol-kartya-szimbolum-es-koponya.webp", "desc": "Patinás gyűrű sebészeti acélból, kártya szimbólum és koponya mintázatban.", "price": 4140, "discount": null, "url": "https://ekszer-eshop.hu/7228-gyuru-nemesacelbol-kartya-szimbolum-es-koponya.html#pa7228_13191", "partner": "ekszereshop", "category_path": "", "findora_main": "divat", "cat": "divat"}, {"id": "7228_13194", "title": "Gyűrű nemesacélból - kártya szimbólum és koponya - Nagyság: 56", "img": "https://ekszer-eshop.hu/7228-9203/gyuru-nemesacelbol-kartya-szimbolum-es-koponya.webp", "desc": "Patinás gyűrű sebészeti acélból, kártya szimbólum és koponya mintázatban.", "price": 4140, "discount": null, "url": "https://ekszer-eshop.hu/7228-gyuru-nemesacelbol-kartya-szimbolum-es-koponya.html#pa7228_13194", "partner": "ekszereshop", "category_path": "", "findora_main": "divat", "cat": "divat"}, {"id": "7228_13195", "title": "Gyűrű nemesacélból - kártya szimbólum és koponya - Nagyság: 57", "img": "https://ekszer-eshop.hu/7228-9203/gyuru-nemesacelbol-kartya-szimbolum-es-koponya.webp", "desc": "Patinás gyűrű sebészeti acélból, kártya szimbólum és koponya mintázatban.", "price": 4140, "discount": null, "url": "https://ekszer-eshop.hu/7228-gyuru-nemesacelbol-kartya-szimbolum-es-koponya.html#pa7228_13195", "partner": "ekszereshop", "category_path": "", "findora_main": "divat", "cat": "divat"}, {"id": "7228_13196", "title": "Gyűrű nemesacélból - kártya szimbólum és koponya - Nagyság: 58", "img": "https://ekszer-eshop.hu/7228-9203/gyuru-nemesacelbol-kartya-szimbolum-es-koponya.webp", "desc": "Patinás gyűrű sebészeti acélból, kártya szimbólum és koponya mintázatban.", "price": 4140, "discount": null, "url": "https://ekszer-eshop.hu/7228-gyuru-nemesacelbol-kartya-szimbolum-es-koponya.html#pa7228_13196", "partner": "ekszereshop", "category_path": "", "findora_main": "divat", "cat": "divat"}, {"id": "7228_13197", "title": "Gyűrű nemesacélból - kártya szimbólum és koponya - Nagyság: 59", "img": "https://ekszer-eshop.hu/7228-9203/gyuru-nemesacelbol-kartya-szimbolum-es-koponya.webp", "desc": "Patinás gyűrű sebészeti acélból, kártya szimbólum és koponya mintázatban.", "price": 4140, "discount": null, "url": "https://ekszer-eshop.hu/7228-gyuru-nemesacelbol-kartya-szimbolum-es-koponya.html#pa7228_13197", "partner": "ekszereshop", "category_path": "", "findora_main": "divat", "cat": "divat"}, {"id": "7228_13203", "title": "Gyűrű nemesacélból - kártya szimbólum és koponya - Nagyság: 60", "img": "https://ekszer-eshop.hu/7228-9203/gyuru-nemesacelbol-kartya-szimbolum-es-koponya.webp", "desc": "Patinás gyűrű sebészeti acélból, kártya szimbólum és koponya mintázatban.", "price": 4140, "discount": null, "url": "https://ekszer-eshop.hu/7228-gyuru-nemesacelbol-kartya-szimbolum-es-koponya.html#pa7228_13203", "partner": "ekszereshop", "category_path": "", "findora_main": "divat", "cat": "divat"}, {"id": "7228_33734", "title": "Gyűrű nemesacélból - kártya szimbólum és koponya - Nagyság: 61", "img": "https://ekszer-eshop.hu/7228-9203/gyuru-nemesacelbol-kartya-szimbolum-es-koponya.webp", "desc": "Patinás gyűrű sebészeti acélból, kártya szimbólum és koponya mintázatban.", "price": 4140, "discount": null, "url": "https://ekszer-eshop.hu/7228-gyuru-nemesacelbol-kartya-szimbolum-es-koponya.html#pa7228_33734", "partner": "ekszereshop", "category_path": "", "findora_main": "divat", "cat": "divat"}, {"id": "7228_28146", "title": "Gyűrű nemesacélból - kártya szimbólum és koponya - Nagyság: 62", "img": "https://ekszer-eshop.hu/7228-9203/gyuru-nemesacelbol-kartya-szimbolum-es-koponya.webp", "desc": "Patinás gyűrű sebészeti acélból, kártya szimbólum és koponya mintázatban.", "price": 4140, "discount": null, "url": "https://ekszer-eshop.hu/7228-gyuru-nemesacelbol-kartya-szimbolum-es-koponya.html#pa7228_28146", "partner": "ekszereshop", "category_path": "", "findora_main": "divat", "cat": "divat"}, {"id": "7228_13198", "title": "Gyűrű nemesacélból - kártya szimbólum és koponya - Nagyság: 63", "img": "https://ekszer-eshop.hu/7228-9203/gyuru-nemesacelbol-kartya-szimbolum-es-koponya.webp", "desc": "Patinás gyűrű sebészeti acélból, kártya szimbólum és koponya mintázatban.", "price": 4140, "discount": null, "url": "https://ekszer-eshop.hu/7228-gyuru-nemesacelbol-kartya-szimbolum-es-koponya.html#pa7228_13198", "partner": "ekszereshop", "category_path": "", "findora_main": "divat", "cat": "divat"}, {"id": "7228_13199", "title": "Gyűrű nemesacélból - kártya szimbólum és koponya - Nagyság: 64", "img": "https://ekszer-eshop.hu/7228-9203/gyuru-nemesacelbol-kartya-szimbolum-es-koponya.webp", "desc": "Patinás gyűrű sebészeti acélból, kártya szimbólum és koponya mintázatban.", "price": 4140, "discount": null, "url": "https://ekszer-eshop.hu/7228-gyuru-nemesacelbol-kartya-szimbolum-es-koponya.html#pa7228_13199", "partner": "ekszereshop", "category_path": "", "findora_main": "divat", "cat": "divat"}, {"id": "7228_13200", "title": "Gyűrű nemesacélból - kártya szimbólum és koponya - Nagyság: 65", "img": "https://ekszer-eshop.hu/7228-9203/gyuru-nemesacelbol-kartya-szimbolum-es-koponya.webp", "desc": "Patinás gyűrű sebészeti acélból, kártya szimbólum és koponya mintázatban.", "price": 4140, "discount": null, "url": "https://ekszer-eshop.hu/7228-gyuru-nemesacelbol-kartya-szimbolum-es-koponya.html#pa7228_13200", "partner": "ekszereshop", "category_path": "", "findora_main": "divat", "cat": "divat"}, {"id": "7228_28147", "title": "Gyűrű nemesacélból - kártya szimbólum és koponya - Nagyság: 66", "img": "https://ekszer-eshop.hu/7228-9203/gyuru-nemesacelbol-kartya-szimbolum-es-koponya.webp", "desc": "Patinás gyűrű sebészeti acélból, kártya szimbólum és koponya mintázatban.", "price": 4140, "discount": null, "url": "https://ekszer-eshop.hu/7228-gyuru-nemesacelbol-kartya-szimbolum-es-koponya.html#pa7228_28147", "partner": "ekszereshop", "category_path": "", "findora_main": "divat", "cat": "divat"}]}