{"items": [{"id": "967_7747", "title": "UV fültágító alagút - csavarzár, háromféle színben - Vastagság: 10 mm, A piercing színe: Kék", "img": "https://ekszer-eshop.hu/967-1209/uv-fultagito-alagut-csavarzar-haromfele-szinben.webp", "desc": "Egyszerű fültágító alagút UV akril anyagból, csavarzárral.", "price": 4455, "discount": null, "url": "https://ekszer-eshop.hu/fultagito-alagutak/967-uv-fultagito-alagut-csavarzar-haromfele-szinben.html#pa967_7747", "partner": "ekszereshop", "category_path": "", "findora_main": "divat", "cat": "divat"}, {"id": "967_7744", "title": "UV fültágító alagút - csavarzár, háromféle színben - Vastagság: 10 mm, A piercing színe: Fekete", "img": "https://ekszer-eshop.hu/967-1209/uv-fultagito-alagut-csavarzar-haromfele-szinben.webp", "desc": "Egyszerű fültágító alagút UV akril anyagból, csavarzárral.", "price": 4455, "discount": null, "url": "https://ekszer-eshop.hu/fultagito-alagutak/967-uv-fultagito-alagut-csavarzar-haromfele-szinben.html#pa967_7744", "partner": "ekszereshop", "category_path": "", "findora_main": "divat", "cat": "divat"}, {"id": "967_46614", "title": "UV fültágító alagút - csavarzár, háromféle színben - Vastagság: 12 mm, A piercing színe: Kék", "img": "https://ekszer-eshop.hu/967-1209/uv-fultagito-alagut-csavarzar-haromfele-szinben.webp", "desc": "Egyszerű fültágító alagút UV akril anyagból, csavarzárral.", "price": 4745, "discount": null, "url": "https://ekszer-eshop.hu/fultagito-alagutak/967-uv-fultagito-alagut-csavarzar-haromfele-szinben.html#pa967_46614", "partner": "ekszereshop", "category_path": "", "findora_main": "divat", "cat": "divat"}, {"id": "967_46615", "title": "UV fültágító alagút - csavarzár, háromféle színben - Vastagság: 12 mm, A piercing színe: Fekete", "img": "https://ekszer-eshop.hu/967-1209/uv-fultagito-alagut-csavarzar-haromfele-szinben.webp", "desc": "Egyszerű fültágító alagút UV akril anyagból, csavarzárral.", "price": 4745, "discount": null, "url": "https://ekszer-eshop.hu/fultagito-alagutak/967-uv-fultagito-alagut-csavarzar-haromfele-szinben.html#pa967_46615", "partner": "ekszereshop", "category_path": "", "findora_main": "divat", "cat": "divat"}, {"id": "967_8567", "title": "UV fültágító alagút - csavarzár, háromféle színben - Vastagság: 14 mm, A piercing színe: Fekete", "img": "https://ekszer-eshop.hu/967-1209/uv-fultagito-alagut-csavarzar-haromfele-szinben.webp", "desc": "Egyszerű fültágító alagút UV akril anyagból, csavarzárral.", "price": 4990, "discount": null, "url": "https://ekszer-eshop.hu/fultagito-alagutak/967-uv-fultagito-alagut-csavarzar-haromfele-szinben.html#pa967_8567", "partner": "ekszereshop", "category_path": "", "findora_main": "divat", "cat": "divat"}, {"id": "967_8566", "title": "UV fültágító alagút - csavarzár, háromféle színben - Vastagság: 14 mm, A piercing színe: Sötétkék", "img": "https://ekszer-eshop.hu/967-1209/uv-fultagito-alagut-csavarzar-haromfele-szinben.webp", "desc": "Egyszerű fültágító alagút UV akril anyagból, csavarzárral.", "price": 4990, "discount": null, "url": "https://ekszer-eshop.hu/fultagito-alagutak/967-uv-fultagito-alagut-csavarzar-haromfele-szinben.html#pa967_8566", "partner": "ekszereshop", "category_path": "", "findora_main": "divat", "cat": "divat"}, {"id": "967_58171", "title": "UV fültágító alagút - csavarzár, háromféle színben - Vastagság: 16  mm, A piercing színe: Kék", "img": "https://ekszer-eshop.hu/967-1209/uv-fultagito-alagut-csavarzar-haromfele-szinben.webp", "desc": "Egyszerű fültágító alagút UV akril anyagból, csavarzárral.", "price": 5115, "discount": null, "url": "https://ekszer-eshop.hu/fultagito-alagutak/967-uv-fultagito-alagut-csavarzar-haromfele-szinben.html#pa967_58171", "partner": "ekszereshop", "category_path": "", "findora_main": "divat", "cat": "divat"}, {"id": "967_58169", "title": "UV fültágító alagút - csavarzár, háromféle színben - Vastagság: 16  mm, A piercing színe: Fekete", "img": "https://ekszer-eshop.hu/967-1209/uv-fultagito-alagut-csavarzar-haromfele-szinben.webp", "desc": "Egyszerű fültágító alagút UV akril anyagból, csavarzárral.", "price": 5115, "discount": null, "url": "https://ekszer-eshop.hu/fultagito-alagutak/967-uv-fultagito-alagut-csavarzar-haromfele-szinben.html#pa967_58169", "partner": "ekszereshop", "category_path": "", "findora_main": "divat", "cat": "divat"}, {"id": "967_58170", "title": "UV fültágító alagút - csavarzár, háromféle színben - Vastagság: 19 mm, A piercing színe: Fekete", "img": "https://ekszer-eshop.hu/967-1209/uv-fultagito-alagut-csavarzar-haromfele-szinben.webp", "desc": "Egyszerű fültágító alagút UV akril anyagból, csavarzárral.", "price": 5200, "discount": null, "url": "https://ekszer-eshop.hu/fultagito-alagutak/967-uv-fultagito-alagut-csavarzar-haromfele-szinben.html#pa967_58170", "partner": "ekszereshop", "category_path": "", "findora_main": "divat", "cat": "divat"}, {"id": "967_2307", "title": "UV fültágító alagút - csavarzár, háromféle színben - Vastagság: 8 mm, A piercing színe: Kék", "img": "https://ekszer-eshop.hu/967-1209/uv-fultagito-alagut-csavarzar-haromfele-szinben.webp", "desc": "Egyszerű fültágító alagút UV akril anyagból, csavarzárral.", "price": 4125, "discount": null, "url": "https://ekszer-eshop.hu/fultagito-alagutak/967-uv-fultagito-alagut-csavarzar-haromfele-szinben.html#pa967_2307", "partner": "ekszereshop", "category_path": "", "findora_main": "divat", "cat": "divat"}, {"id": "967_2308", "title": "UV fültágító alagút - csavarzár, háromféle színben - Vastagság: 8 mm, A piercing színe: Fekete", "img": "https://ekszer-eshop.hu/967-1209/uv-fultagito-alagut-csavarzar-haromfele-szinben.webp", "desc": "Egyszerű fültágító alagút UV akril anyagból, csavarzárral.", "price": 4125, "discount": null, "url": "https://ekszer-eshop.hu/fultagito-alagutak/967-uv-fultagito-alagut-csavarzar-haromfele-szinben.html#pa967_2308", "partner": "ekszereshop", "category_path": "", "findora_main": "divat", "cat": "divat"}, {"id": "1036_2311", "title": "Köldök ékszer - banán és nagy kerek cirkónia - A cirkónia színe: Aquakék - Q", "img": "https://ekszer-eshop.hu/1036-1288/koldok-ekszer-banan-es-nagy-kerek-cirkonia.webp", "desc": "Köldök piercing - belly ring, a banán végén egy nagy kerek cirkónia kővel, többféle színben.", "price": 4020, "discount": null, "url": "https://ekszer-eshop.hu/1036-koldok-ekszer-banan-es-nagy-kerek-cirkonia.html#pa1036_2311", "partner": "ekszereshop", "category_path": "", "findora_main": "divat", "cat": "divat"}, {"id": "1036_2313", "title": "Köldök ékszer - banán és nagy kerek cirkónia - A cirkónia színe: Átlátszó - C", "img": "https://ekszer-eshop.hu/1036-1288/koldok-ekszer-banan-es-nagy-kerek-cirkonia.webp", "desc": "Köldök piercing - belly ring, a banán végén egy nagy kerek cirkónia kővel, többféle színben.", "price": 4020, "discount": null, "url": "https://ekszer-eshop.hu/1036-koldok-ekszer-banan-es-nagy-kerek-cirkonia.html#pa1036_2313", "partner": "ekszereshop", "category_path": "", "findora_main": "divat", "cat": "divat"}, {"id": "1036_17345", "title": "Köldök ékszer - banán és nagy kerek cirkónia - A cirkónia színe: Kék - B", "img": "https://ekszer-eshop.hu/1036-1288/koldok-ekszer-banan-es-nagy-kerek-cirkonia.webp", "desc": "Köldök piercing - belly ring, a banán végén egy nagy kerek cirkónia kővel, többféle színben.", "price": 4020, "discount": null, "url": "https://ekszer-eshop.hu/1036-koldok-ekszer-banan-es-nagy-kerek-cirkonia.html#pa1036_17345", "partner": "ekszereshop", "category_path": "", "findora_main": "divat", "cat": "divat"}, {"id": "1036_2312", "title": "Köldök ékszer - banán és nagy kerek cirkónia - A cirkónia színe: Piros - R", "img": "https://ekszer-eshop.hu/1036-1288/koldok-ekszer-banan-es-nagy-kerek-cirkonia.webp", "desc": "Köldök piercing - belly ring, a banán végén egy nagy kerek cirkónia kővel, többféle színben.", "price": 4020, "discount": null, "url": "https://ekszer-eshop.hu/1036-koldok-ekszer-banan-es-nagy-kerek-cirkonia.html#pa1036_2312", "partner": "ekszereshop", "category_path": "", "findora_main": "divat", "cat": "divat"}, {"id": "1036_2314", "title": "Köldök ékszer - banán és nagy kerek cirkónia - A cirkónia színe: Rózsaszín - P", "img": "https://ekszer-eshop.hu/1036-1288/koldok-ekszer-banan-es-nagy-kerek-cirkonia.webp", "desc": "Köldök piercing - belly ring, a banán végén egy nagy kerek cirkónia kővel, többféle színben.", "price": 4020, "discount": null, "url": "https://ekszer-eshop.hu/1036-koldok-ekszer-banan-es-nagy-kerek-cirkonia.html#pa1036_2314", "partner": "ekszereshop", "category_path": "", "findora_main": "divat", "cat": "divat"}, {"id": "1036_2316", "title": "Köldök ékszer - banán és nagy kerek cirkónia - A cirkónia színe: Tanzanit - TZ", "img": "https://ekszer-eshop.hu/1036-1288/koldok-ekszer-banan-es-nagy-kerek-cirkonia.webp", "desc": "Köldök piercing - belly ring, a banán végén egy nagy kerek cirkónia kővel, többféle színben.", "price": 4020, "discount": null, "url": "https://ekszer-eshop.hu/1036-koldok-ekszer-banan-es-nagy-kerek-cirkonia.html#pa1036_2316", "partner": "ekszereshop", "category_path": "", "findora_main": "divat", "cat": "divat"}, {"id": "1036_2315", "title": "Köldök ékszer - banán és nagy kerek cirkónia - A cirkónia színe: Világoszöld - G", "img": "https://ekszer-eshop.hu/1036-1288/koldok-ekszer-banan-es-nagy-kerek-cirkonia.webp", "desc": "Köldök piercing - belly ring, a banán végén egy nagy kerek cirkónia kővel, többféle színben.", "price": 4020, "discount": null, "url": "https://ekszer-eshop.hu/1036-koldok-ekszer-banan-es-nagy-kerek-cirkonia.html#pa1036_2315", "partner": "ekszereshop", "category_path": "", "findora_main": "divat", "cat": "divat"}, {"id": "1078_52339", "title": "Fekete fültágító alagút - nyereg forma, UV akril - Vastagság: 10 mm", "img": "https://ekszer-eshop.hu/1078-1331/fekete-fultagito-alagut-nyereg-forma-uv-akril.webp", "desc": "Fültágító alagút - UV akril anyag, nyereg forma, fekete színben.", "price": 4235, "discount": null, "url": "https://ekszer-eshop.hu/fultagito-alagutak/1078-fekete-fultagito-alagut-nyereg-forma-uv-akril.html#pa1078_52339", "partner": "ekszereshop", "category_path": "", "findora_main": "divat", "cat": "divat"}, {"id": "1078_25981", "title": "Fekete fültágító alagút - nyereg forma, UV akril - Vastagság: 3 mm", "img": "https://ekszer-eshop.hu/1078-1331/fekete-fultagito-alagut-nyereg-forma-uv-akril.webp", "desc": "Fültágító alagút - UV akril anyag, nyereg forma, fekete színben.", "price": 4235, "discount": null, "url": "https://ekszer-eshop.hu/fultagito-alagutak/1078-fekete-fultagito-alagut-nyereg-forma-uv-akril.html#pa1078_25981", "partner": "ekszereshop", "category_path": "", "findora_main": "divat", "cat": "divat"}]}