[{"title":"HP LT2000KEXVC | 2TB PCIe Mixed Use HH HL Workload Accelerator","price":445.53,"currency":"","url":"https://www.awin1.com/pclick.php?p=41622622968&a=2637236&m=115128","img":"https://images.gotodirect.com/uploads/products/2025/3/67d238621c952.jpg","category":"","brand":"","in_stock":null,"partner":"advadv"},{"title":"Intel SRKHX | Xeon Gold 8368Q 38 Cores 2.60GHz LGA4189 Processor","price":2382.06,"currency":"","url":"https://www.awin1.com/pclick.php?p=41622622966&a=2637236&m=115128","img":"https://images.gotodirect.com/uploads/products/2025/3/67d238668ffc7.jpg","category":"","brand":"","in_stock":null,"partner":"advadv"},{"title":"HPE P12018-001 | 3.30GHz LGA3647 Gold 6246 12-Core Processor","price":589.86,"currency":"","url":"https://www.awin1.com/pclick.php?p=41622622965&a=2637236&m=115128","img":"https://images.gotodirect.com/uploads/products/2025/3/67d23867a00d5.jpg","category":"","brand":"","in_stock":null,"partner":"advadv"},{"title":"Intel PK8072205559000 | Xeon Gold 5515+ 8-C 3.2GHz LGA4677 Processor","price":1199.23,"currency":"","url":"https://www.awin1.com/pclick.php?p=41622622962&a=2637236&m=115128","img":"https://images.gotodirect.com/uploads/products/2025/3/67d23868d460a.jpg","category":"","brand":"","in_stock":null,"partner":"advadv"},{"title":"Toshiba MG09SCA12TE | Enterprise Capacity MG09 12TB 7200RPM SAS 3.5-inch Hard Drive","price":504.64,"currency":"","url":"https://www.awin1.com/pclick.php?p=41622622960&a=2637236&m=115128","img":"https://images.gotodirect.com/uploads/products/2025/3/67d2386b2781d.jpg","category":"","brand":"","in_stock":null,"partner":"advadv"},{"title":"Intel SRFPM | Xeon Gold 5218T 16-Core 2.10GHz LGA3647 Processor","price":996.07,"currency":"","url":"https://www.awin1.com/pclick.php?p=41622622959&a=2637236&m=115128","img":"https://images.gotodirect.com/uploads/products/2025/3/67d2386c4e4f0.jpg","category":"","brand":"","in_stock":null,"partner":"advadv"},{"title":"Intel PK8072205560100 | Xeon Gold 6548N 32-C 2.8GHz LGA4677 Processor","price":3717.86,"currency":"","url":"https://www.awin1.com/pclick.php?p=41622622958&a=2637236&m=115128","img":"https://images.gotodirect.com/uploads/products/2025/3/67d2386cbca9f.jpg","category":"","brand":"","in_stock":null,"partner":"advadv"},{"title":"Delta DPS-650JB B | 650W ATX Power Supply for PowerVault TL2000","price":88.4,"currency":"","url":"https://www.awin1.com/pclick.php?p=41622622957&a=2637236&m=115128","img":"https://images.gotodirect.com/uploads/products/2025/3/67d2386d6eed5.jpg","category":"","brand":"","in_stock":null,"partner":"advadv"},{"title":"Fortinet FS-Power Supply-150 | 150W Redundant Power Supply for FortiSwitch 524D-FPoE","price":585.34,"currency":"","url":"https://www.awin1.com/pclick.php?p=41622622956&a=2637236&m=115128","img":"https://images.gotodirect.com/uploads/products/2025/3/67d2386e969c6.jpg","category":"","brand":"","in_stock":null,"partner":"advadv"},{"title":"Intel PK8071305118701 | Xeon Gold 5415+ 8-Core 2.9GHz 22.5MB Processor","price":1228.05,"currency":"","url":"https://www.awin1.com/pclick.php?p=41622622955&a=2637236&m=115128","img":"https://images.gotodirect.com/uploads/products/2025/3/67d2386fad9a9.jpg","category":"","brand":"","in_stock":null,"partner":"advadv"},{"title":"Intel PK8071305120401 | Xeon Gold 5412U 24-Core 2.10GHz 45MB Processor","price":1560.64,"currency":"","url":"https://www.awin1.com/pclick.php?p=41622622953&a=2637236&m=115128","img":"https://images.gotodirect.com/uploads/products/2025/3/67d23871e92a9.jpg","category":"","brand":"","in_stock":null,"partner":"advadv"},{"title":"Intel PK8072205559700 | Xeon Gold 6548Y+ 32-C 2.5GHz LGA4677 Processor","price":3575.24,"currency":"","url":"https://www.awin1.com/pclick.php?p=41622622952&a=2637236&m=115128","img":"https://images.gotodirect.com/uploads/products/2025/3/67d23872bfc8c.jpg","category":"","brand":"","in_stock":null,"partner":"advadv"},{"title":"Intel PK8072205559100 | Xeon Silver 4514Y 16-C 2GHz LGA4677 Processor","price":1073.5,"currency":"","url":"https://www.awin1.com/pclick.php?p=41622622951&a=2637236&m=115128","img":"https://images.gotodirect.com/uploads/products/2025/3/67d2387312e5f.jpg","category":"","brand":"","in_stock":null,"partner":"advadv"},{"title":"HPE P67824-B21 | 2.4GHz LGA4677 Xeon Silver 4510 12-Core Processor","price":900.61,"currency":"","url":"https://www.awin1.com/pclick.php?p=41622622950&a=2637236&m=115128","img":"https://images.gotodirect.com/uploads/products/2025/3/67d23873ba9f4.jpg","category":"","brand":"","in_stock":null,"partner":"advadv"},{"title":"Intel SRN4G | Xeon w5-2545 12-Core 3.50GHz LGA4677 Processor","price":1317.55,"currency":"","url":"https://www.awin1.com/pclick.php?p=41622622949&a=2637236&m=115128","img":"https://images.gotodirect.com/uploads/products/2025/3/67d238741ebc7.jpg","category":"","brand":"","in_stock":null,"partner":"advadv"},{"title":"HPE P60428-001 | 2.6GHz LGA4677 Xeon Gold 6442Y 24-Core Processor","price":3757.15,"currency":"","url":"https://www.awin1.com/pclick.php?p=41622622948&a=2637236&m=115128","img":"https://images.gotodirect.com/uploads/products/2025/3/67d23874ced27.jpg","category":"","brand":"","in_stock":null,"partner":"advadv"},{"title":"Intel SRMXC | Xeon E-2434 4-Core 3.40GHz LGA1700 Processor","price":477.36,"currency":"","url":"https://www.awin1.com/pclick.php?p=41622622947&a=2637236&m=115128","img":"https://images.gotodirect.com/uploads/products/2025/3/67d238753b0f9.jpg","category":"","brand":"","in_stock":null,"partner":"advadv"},{"title":"Dell 5DKKV | 2GHz LGA4677 Intel Xeon Silver 4410Y 12-Core Processor","price":880.27,"currency":"","url":"https://www.awin1.com/pclick.php?p=41622622946&a=2637236&m=115128","img":"https://images.gotodirect.com/uploads/products/2025/3/67d23875de320.jpg","category":"","brand":"","in_stock":null,"partner":"advadv"},{"title":"Intel SRM9J | Xeon w3-2435 8-Core 3.10GHz LGA4677 Processor","price":1054.29,"currency":"","url":"https://www.awin1.com/pclick.php?p=41622622945&a=2637236&m=115128","img":"https://images.gotodirect.com/uploads/products/2025/3/67d238766684c.jpg","category":"","brand":"","in_stock":null,"partner":"advadv"},{"title":"Dell 6PXRK | 2.00GHz LGA4677 Intel Xeon Gold 6438Y+ 32-Core Processor","price":4119.12,"currency":"","url":"https://www.awin1.com/pclick.php?p=41622622943&a=2637236&m=115128","img":"https://images.gotodirect.com/uploads/products/2025/3/67d238777338a.jpg","category":"","brand":"","in_stock":null,"partner":"advadv"},{"title":"Dell VPDGC | QLogic 2770 32Gbps 1-Port Fiber Channel PCIe FH Host Bus Adapter","price":913.22,"currency":"","url":"https://www.awin1.com/pclick.php?p=41622622942&a=2637236&m=115128","img":"https://images.gotodirect.com/uploads/products/2025/3/67d238782cf77.jpg","category":"","brand":"","in_stock":null,"partner":"advadv"},{"title":"Dell DPSN-350CBE | 350W 100-240V AC 6.0A 50-60Hz Power Supply","price":174.84,"currency":"","url":"https://www.awin1.com/pclick.php?p=41622622939&a=2637236&m=115128","img":"https://images.gotodirect.com/uploads/products/2025/3/67d23879bb654.jpg","category":"","brand":"","in_stock":null,"partner":"advadv"},{"title":"Dell 338-BZRW | 2.45GHz Socket SP3 EPYC 7763 64-Core Processor","price":2316.57,"currency":"","url":"https://www.awin1.com/pclick.php?p=41622622938&a=2637236&m=115128","img":"https://images.gotodirect.com/uploads/products/2025/3/67d2387a51ef0.jpg","category":"","brand":"","in_stock":null,"partner":"advadv"},{"title":"Intel SR2X5 | Xeon Phi 7210F 64-Core 1.30GHz LGA3647 Processor","price":557.15,"currency":"","url":"https://www.awin1.com/pclick.php?p=41622622937&a=2637236&m=115128","img":"https://images.gotodirect.com/uploads/products/2025/3/67d2387ad5ca4.jpg","category":"","brand":"","in_stock":null,"partner":"advadv"},{"title":"HPE P60430-001 | 3.70GHz LGA4677 Xeon Gold 6434 8-Core Processor","price":3548.88,"currency":"","url":"https://www.awin1.com/pclick.php?p=41622622936&a=2637236&m=115128","img":"https://images.gotodirect.com/uploads/products/2025/3/67d2387b4ad46.jpg","category":"","brand":"","in_stock":null,"partner":"advadv"},{"title":"Intel SRMX9 | Xeon E-2486 6-Core 3.50GHz LGA1700 Processor","price":867.84,"currency":"","url":"https://www.awin1.com/pclick.php?p=41622622935&a=2637236&m=115128","img":"https://images.gotodirect.com/uploads/products/2025/3/67d2387be6cb4.jpg","category":"","brand":"","in_stock":null,"partner":"advadv"},{"title":"Dell 338-CLWP | 2.00GHz LGA4677 Gold 6438N 32-Core Processor","price":4640.76,"currency":"","url":"https://www.awin1.com/pclick.php?p=41622622934&a=2637236&m=115128","img":"https://images.gotodirect.com/uploads/products/2025/3/67d2387c5b5b7.jpg","category":"","brand":"","in_stock":null,"partner":"advadv"},{"title":"Intel SRM9L | Xeon w3-2423 6-Core 2.1GHz 15MB LGA4677 Processor","price":571.78,"currency":"","url":"https://www.awin1.com/pclick.php?p=41622622932&a=2637236&m=115128","img":"https://images.gotodirect.com/uploads/products/2025/3/67d2387e58c38.jpg","category":"","brand":"","in_stock":null,"partner":"advadv"},{"title":"EMC 005052460 | 7.68TB SAS 12GB/s 2.5-inch Enterprise Solid State Drive","price":1080.28,"currency":"","url":"https://www.awin1.com/pclick.php?p=41622622931&a=2637236&m=115128","img":"https://images.gotodirect.com/uploads/products/2025/3/67d2387f3f1be.jpg","category":"","brand":"","in_stock":null,"partner":"advadv"},{"title":"HPE P60444-001 | 2.4GHz LGA4677 Xeon Gold 6448H 32-Core Processor","price":4808.16,"currency":"","url":"https://www.awin1.com/pclick.php?p=41622622929&a=2637236&m=115128","img":"https://images.gotodirect.com/uploads/products/2025/3/67d2388047683.jpg","category":"","brand":"","in_stock":null,"partner":"advadv"},{"title":"HPE P67825-B21 | 2.2GHz LGA4677 Xeon Silver 4516Y+ 24-Core Processor","price":1979.13,"currency":"","url":"https://www.awin1.com/pclick.php?p=41622622928&a=2637236&m=115128","img":"https://images.gotodirect.com/uploads/products/2025/3/67d238808325e.jpg","category":"","brand":"","in_stock":null,"partner":"advadv"},{"title":"Intel SRN6K | Xeon Silver 4516Y+ 24-Core 2.2GHz LGA4677 Processor","price":1979.13,"currency":"","url":"https://www.awin1.com/pclick.php?p=41622622926&a=2637236&m=115128","img":"https://images.gotodirect.com/uploads/products/2025/3/67d23881b6cdf.jpg","category":"","brand":"","in_stock":null,"partner":"advadv"},{"title":"Dell FFT27 | 2.45GHz Socket SP3 EPYC 7763 64-Core Processor","price":2316.57,"currency":"","url":"https://www.awin1.com/pclick.php?p=41622622924&a=2637236&m=115128","img":"https://images.gotodirect.com/uploads/products/2025/3/67d23882d6ef9.jpg","category":"","brand":"","in_stock":null,"partner":"advadv"},{"title":"Dell 338-CCUR | 2.3GHz LGA4189 Xeon Platinum 8352M 32-Core Processor","price":3072.6,"currency":"","url":"https://www.awin1.com/pclick.php?p=41622622923&a=2637236&m=115128","img":"https://images.gotodirect.com/uploads/products/2025/3/67d23883ade42.jpg","category":"","brand":"","in_stock":null,"partner":"advadv"},{"title":"Dell 6NG2Y | 2.1GHz LGA4189 Intel Xeon Gold 5318Y 24-Core Processor","price":2368.74,"currency":"","url":"https://www.awin1.com/pclick.php?p=41622622921&a=2637236&m=115128","img":"https://images.gotodirect.com/uploads/products/2025/3/67d2388510a04.jpg","category":"","brand":"","in_stock":null,"partner":"advadv"},{"title":"Dell 338-CFEQ | 2.20GHz Socket SP3 EPYC 7773X 64-Core Processor","price":4191.48,"currency":"","url":"https://www.awin1.com/pclick.php?p=41622622920&a=2637236&m=115128","img":"https://images.gotodirect.com/uploads/products/2025/3/67d238863910f.jpg","category":"","brand":"","in_stock":null,"partner":"advadv"},{"title":"HPE P50797-B21 | 3.70GHz LGA4677 Xeon Gold 6434 8-Core Processor","price":3548.88,"currency":"","url":"https://www.awin1.com/pclick.php?p=41622622919&a=2637236&m=115128","img":"https://images.gotodirect.com/uploads/products/2025/3/67d238865ed68.jpg","category":"","brand":"","in_stock":null,"partner":"advadv"},{"title":"Intel SRMX8 | Xeon E-2468 8-Core 2.60GHz LGA1700 Processor","price":780.83,"currency":"","url":"https://www.awin1.com/pclick.php?p=41622622917&a=2637236&m=115128","img":"https://images.gotodirect.com/uploads/products/2025/3/67d2388825d3f.jpg","category":"","brand":"","in_stock":null,"partner":"advadv"},{"title":"Intel SRN76 | Xeon w5-3535X 20-Core 2.90GHz LGA4677 Processor","price":2645.13,"currency":"","url":"https://www.awin1.com/pclick.php?p=41622622913&a=2637236&m=115128","img":"https://images.gotodirect.com/uploads/products/2025/3/67d2388a430d8.jpg","category":"","brand":"","in_stock":null,"partner":"advadv"},{"title":"Intel SRMXD | Xeon E-2414 4-Core 2.60GHz LGA1700 Processor","price":395.46,"currency":"","url":"https://www.awin1.com/pclick.php?p=41622622912&a=2637236&m=115128","img":"https://images.gotodirect.com/uploads/products/2025/3/67d2388a5549c.jpg","category":"","brand":"","in_stock":null,"partner":"advadv"},{"title":"Dell GMGPF | 3.6GHz LGA4189 Intel Xeon Gold 6334 8-Core Processor","price":3021.84,"currency":"","url":"https://www.awin1.com/pclick.php?p=41622622911&a=2637236&m=115128","img":"https://images.gotodirect.com/uploads/products/2025/3/67d2388b6519a.jpg","category":"","brand":"","in_stock":null,"partner":"advadv"},{"title":"Dell 338-CLVZ | 2.00GHz LGA4677 Xeon Gold 6438Y+ 32-Core Processor","price":4119.12,"currency":"","url":"https://www.awin1.com/pclick.php?p=41622622910&a=2637236&m=115128","img":"https://images.gotodirect.com/uploads/products/2025/3/67d2388b7f286.jpg","category":"","brand":"","in_stock":null,"partner":"advadv"},{"title":"HPE P50801-B21 | 2GHz LGA4677 Xeon Silver 4410Y 12-Core Processor","price":880.27,"currency":"","url":"https://www.awin1.com/pclick.php?p=41622622909&a=2637236&m=115128","img":"https://images.gotodirect.com/uploads/products/2025/3/67d2388c683c3.jpg","category":"","brand":"","in_stock":null,"partner":"advadv"},{"title":"Dell 9V9J1 | 2.4GHz LGA4677 Intel Xeon Gold 6448H 32-Core Processor","price":4808.16,"currency":"","url":"https://www.awin1.com/pclick.php?p=41622622908&a=2637236&m=115128","img":"https://images.gotodirect.com/uploads/products/2025/3/67d2388c87b4c.jpg","category":"","brand":"","in_stock":null,"partner":"advadv"},{"title":"Dell TF4VD | 3.60GHz LGA4677 Intel Xeon Gold 6444Y 16-Core Processor","price":5142.96,"currency":"","url":"https://www.awin1.com/pclick.php?p=41622622905&a=2637236&m=115128","img":"https://images.gotodirect.com/uploads/products/2025/3/67d2388eaf690.jpg","category":"","brand":"","in_stock":null,"partner":"advadv"},{"title":"Intel SRM9H | Xeon w5-2445 10-Core 3.1GHz 26.25MB LGA4677 Processor","price":1471.86,"currency":"","url":"https://www.awin1.com/pclick.php?p=41622622902&a=2637236&m=115128","img":"https://images.gotodirect.com/uploads/products/2025/3/67d2388fbe6b5.jpg","category":"","brand":"","in_stock":null,"partner":"advadv"},{"title":"HPE P61447-B21 | 2GHz LGA4677 Xeon Silver 4416+ 20-Core Processor","price":1848.15,"currency":"","url":"https://www.awin1.com/pclick.php?p=41622622898&a=2637236&m=115128","img":"https://images.gotodirect.com/uploads/products/2025/3/67d23892de4fb.jpg","category":"","brand":"","in_stock":null,"partner":"advadv"},{"title":"Intel SRN4F | Xeon w5-2555X 14-Core 3.30GHz LGA4677 Processor","price":1716.06,"currency":"","url":"https://www.awin1.com/pclick.php?p=41622622897&a=2637236&m=115128","img":"https://images.gotodirect.com/uploads/products/2025/3/67d2389367c14.jpg","category":"","brand":"","in_stock":null,"partner":"advadv"},{"title":"Dell 338-CBOQ | 2.25GHz Socket SP3 EPYC 7702P 64-Core Processor","price":1013.61,"currency":"","url":"https://www.awin1.com/pclick.php?p=41622622896&a=2637236&m=115128","img":"https://images.gotodirect.com/uploads/products/2025/3/67d23893f1dd9.jpg","category":"","brand":"","in_stock":null,"partner":"advadv"},{"title":"Dell 338-CKTH | 2GHz LGA4677 Xeon Gold 5418Y 24-Core Processor","price":2316.57,"currency":"","url":"https://www.awin1.com/pclick.php?p=41622622895&a=2637236&m=115128","img":"https://images.gotodirect.com/uploads/products/2025/3/67d23894804fb.jpg","category":"","brand":"","in_stock":null,"partner":"advadv"},{"title":"HPE P69261-B21 | 2.65GHz Socket SP6 EPYC 8324P 32-Core Processor","price":2587.2,"currency":"","url":"https://www.awin1.com/pclick.php?p=41622622894&a=2637236&m=115128","img":"https://images.gotodirect.com/uploads/products/2025/3/67d238952a777.jpg","category":"","brand":"","in_stock":null,"partner":"advadv"},{"title":"Dell KGFTH | 2.00GHz LGA4677 Intel Xeon Gold 5418Y 24-Core Processor","price":2316.57,"currency":"","url":"https://www.awin1.com/pclick.php?p=41622622891&a=2637236&m=115128","img":"https://images.gotodirect.com/uploads/products/2025/3/67d23896e5d0a.jpg","category":"","brand":"","in_stock":null,"partner":"advadv"},{"title":"Dell 4PW9R | 2.30GHz LGA4189 Xeon Platinum 8352M 32-Core Processor","price":3072.6,"currency":"","url":"https://www.awin1.com/pclick.php?p=41622622890&a=2637236&m=115128","img":"https://images.gotodirect.com/uploads/products/2025/3/67d23897b1c1d.jpg","category":"","brand":"","in_stock":null,"partner":"advadv"},{"title":"Dell KHP1F | 2.00GHz 30MB LGA4677 Xeon Gold 5416S 16-Core Processor","price":1443.0,"currency":"","url":"https://www.awin1.com/pclick.php?p=41622622889&a=2637236&m=115128","img":"https://images.gotodirect.com/uploads/products/2025/3/67d23897f3ceb.jpg","category":"","brand":"","in_stock":null,"partner":"advadv"},{"title":"Intel SRKN1 | Xeon E-2378G 8-Core 2.80GHz LGA1200 Processor","price":1089.76,"currency":"","url":"https://www.awin1.com/pclick.php?p=41622622886&a=2637236&m=115128","img":"https://images.gotodirect.com/uploads/products/2025/3/67d2389a4b3dc.jpg","category":"","brand":"","in_stock":null,"partner":"advadv"},{"title":"Intel SRKN3 | Xeon E-2374G 4-Core 3.70GHz LGA1200 Processor","price":677.66,"currency":"","url":"https://www.awin1.com/pclick.php?p=41622622885&a=2637236&m=115128","img":"https://images.gotodirect.com/uploads/products/2025/3/67d2389a74bf3.jpg","category":"","brand":"","in_stock":null,"partner":"advadv"},{"title":"Intel E5-1650-V4 | Xeon 3.60GHz Server CPU","price":759.07,"currency":"","url":"https://www.awin1.com/pclick.php?p=41622622884&a=2637236&m=115128","img":"https://images.gotodirect.com/uploads/products/2025/3/67d2389b99236.jpg","category":"","brand":"","in_stock":null,"partner":"advadv"},{"title":"Seasonic SSP-300SFB | 300W 100-240V Gold SFX Power Supply","price":170.66,"currency":"","url":"https://www.awin1.com/pclick.php?p=41622622883&a=2637236&m=115128","img":"https://images.gotodirect.com/uploads/products/2025/3/67d2389bb8457.jpg","category":"","brand":"","in_stock":null,"partner":"advadv"},{"title":"Intel CD8069504289900 | Xeon Gold 5218N 16 Core 2.30GHz Processor","price":681.24,"currency":"","url":"https://www.awin1.com/pclick.php?p=41622622881&a=2637236&m=115128","img":"https://images.gotodirect.com/uploads/products/2025/3/67d2389d03ccd.jpg","category":"","brand":"","in_stock":null,"partner":"advadv"},{"title":"Intel SRM9G | Xeon W5-2455x 12-Core 3.20GHz 30MB Processor","price":1423.81,"currency":"","url":"https://www.awin1.com/pclick.php?p=41622622880&a=2637236&m=115128","img":"https://images.gotodirect.com/uploads/products/2025/3/67d2389e2911f.jpg","category":"","brand":"","in_stock":null,"partner":"advadv"},{"title":"Intel SRN6J | Xeon Silver 4514Y 16-Core 2GHz LGA4677 Processor","price":1227.66,"currency":"","url":"https://www.awin1.com/pclick.php?p=41622622878&a=2637236&m=115128","img":"https://images.gotodirect.com/uploads/products/2025/3/67d2389f2e936.jpg","category":"","brand":"","in_stock":null,"partner":"advadv"},{"title":"HPE P60436-001 | 2GHz LGA4677 Intel Xeon Gold 5420+ 28-Core Processor","price":2958.12,"currency":"","url":"https://www.awin1.com/pclick.php?p=41622622875&a=2637236&m=115128","img":"https://images.gotodirect.com/uploads/products/2025/3/67d238a048145.jpg","category":"","brand":"","in_stock":null,"partner":"advadv"},{"title":"Dell G6YYV | 3.10GHz 36MB Intel Xeon Gold 6346 16-Core Processor","price":2221.97,"currency":"","url":"https://www.awin1.com/pclick.php?p=41622622873&a=2637236&m=115128","img":"https://images.gotodirect.com/uploads/products/2025/3/67d238a14eb8f.jpg","category":"","brand":"","in_stock":null,"partner":"advadv"},{"title":"Intel SRM35 | Xeon W5-3425 12-Core 3.20GHz 30MB Processor","price":1533.34,"currency":"","url":"https://www.awin1.com/pclick.php?p=41622622871&a=2637236&m=115128","img":"https://images.gotodirect.com/uploads/products/2025/3/67d238a27b169.jpg","category":"","brand":"","in_stock":null,"partner":"advadv"},{"title":"Dell 4VH89 | 2.3GHz LGA4189 Xeon Silver 4316 20-Core Processor","price":1323.5,"currency":"","url":"https://www.awin1.com/pclick.php?p=41622622868&a=2637236&m=115128","img":"https://images.gotodirect.com/uploads/products/2025/3/67d238a4a9b5e.jpg","category":"","brand":"","in_stock":null,"partner":"advadv"},{"title":"HPE P49638-B21 | 2GHz LGA4677 Xeon Gold 6438N 32-Core Processor","price":4640.76,"currency":"","url":"https://www.awin1.com/pclick.php?p=41622622867&a=2637236&m=115128","img":"https://images.gotodirect.com/uploads/products/2025/3/67d238a4b1daa.jpg","category":"","brand":"","in_stock":null,"partner":"advadv"},{"title":"HPE P03177-B21 | 1000W Titanium Hot-pluggable Power Supply","price":355.68,"currency":"","url":"https://www.awin1.com/pclick.php?p=41622622865&a=2637236&m=115128","img":"https://images.gotodirect.com/uploads/products/2025/3/67d238a604ca2.jpg","category":"","brand":"","in_stock":null,"partner":"advadv"},{"title":"Intel PK8072205503600 | Xeon Gold 6538N 32-C 2.1GHz LGA4677 Processor","price":5019.84,"currency":"","url":"https://www.awin1.com/pclick.php?p=41622622857&a=2637236&m=115128","img":"https://images.gotodirect.com/uploads/products/2025/3/67d238aac9515.jpg","category":"","brand":"","in_stock":null,"partner":"advadv"},{"title":"HPE P67657-001 | 2.20GHz LGA4677 Xeon Gold 6538Y+ 32-Core Processor","price":4725.0,"currency":"","url":"https://www.awin1.com/pclick.php?p=41622622856&a=2637236&m=115128","img":"https://images.gotodirect.com/uploads/products/2025/3/67d238ab57ed1.jpg","category":"","brand":"","in_stock":null,"partner":"advadv"},{"title":"Dell 4X020 | 3.2GHz 12MB LGA1200 Xeon E-2356G 6-Core Processor","price":612.46,"currency":"","url":"https://www.awin1.com/pclick.php?p=41622622855&a=2637236&m=115128","img":"https://images.gotodirect.com/uploads/products/2025/3/67d238abf1c54.jpg","category":"","brand":"","in_stock":null,"partner":"advadv"},{"title":"Dell 2H9F8 | 3.00GHz 39MB LGA4189 Xeon Gold 6354 18-Core Processor","price":3805.92,"currency":"","url":"https://www.awin1.com/pclick.php?p=41622622854&a=2637236&m=115128","img":"https://images.gotodirect.com/uploads/products/2025/3/67d238ac75e27.jpg","category":"","brand":"","in_stock":null,"partner":"advadv"},{"title":"HPE P24705-B21 | 2.20GHz LGA3647 Gold 6238R 28-Core Processor","price":1945.6,"currency":"","url":"https://www.awin1.com/pclick.php?p=41622622853&a=2637236&m=115128","img":"https://images.gotodirect.com/uploads/products/2025/3/67d238ad2ee00.jpg","category":"","brand":"","in_stock":null,"partner":"advadv"},{"title":"HPE P67644-001 | 3.9GHz LGA4677 Intel Xeon Gold 6534 8-Core Processor","price":4216.32,"currency":"","url":"https://www.awin1.com/pclick.php?p=41622622852&a=2637236&m=115128","img":"https://images.gotodirect.com/uploads/products/2025/3/67d238add035b.jpg","category":"","brand":"","in_stock":null,"partner":"advadv"},{"title":"HP 726237-001 | 764W 80 Plus Gold Power Supply for E 3Par StoreServer 7000","price":161.25,"currency":"","url":"https://www.awin1.com/pclick.php?p=41623025661&a=2637236&m=115128","img":"https://images.gotodirect.com/uploads/products/2023/3/640abc1593076.jpg","category":"","brand":"","in_stock":null,"partner":"advadv"},{"title":"HPE P60440-001 | 2.10GHz 45MB Intel Xeon Gold 5412U 24-Core Processor","price":1854.43,"currency":"","url":"https://www.awin1.com/pclick.php?p=41622622850&a=2637236&m=115128","img":"https://images.gotodirect.com/uploads/products/2025/3/67d238aeecf43.jpg","category":"","brand":"","in_stock":null,"partner":"advadv"},{"title":"HPE P24659-B21 | 2.70GHz LGA3647 Gold 6258R 28-Core Processor","price":3265.92,"currency":"","url":"https://www.awin1.com/pclick.php?p=41622622848&a=2637236&m=115128","img":"https://images.gotodirect.com/uploads/products/2025/3/67d238b0153d0.jpg","category":"","brand":"","in_stock":null,"partner":"advadv"},{"title":"Intel SRN6H | Xeon Gold 5515+ 8-Core 3.20GHz LGA4677 Processor","price":1697.19,"currency":"","url":"https://www.awin1.com/pclick.php?p=41622622845&a=2637236&m=115128","img":"https://images.gotodirect.com/uploads/products/2025/3/67d238b1b1f55.jpg","category":"","brand":"","in_stock":null,"partner":"advadv"},{"title":"Intel PK8072205499300 | Xeon Gold 6534 8-Core 3.9GHz LGA4677 Processor","price":4216.32,"currency":"","url":"https://www.awin1.com/pclick.php?p=41622622840&a=2637236&m=115128","img":"https://images.gotodirect.com/uploads/products/2025/3/67d238b489ee0.jpg","category":"","brand":"","in_stock":null,"partner":"advadv"},{"title":"HPE P60446-001 | 2GHz LGA4677 Xeon Gold 6438N 32-Core Processor","price":4640.76,"currency":"","url":"https://www.awin1.com/pclick.php?p=41622622838&a=2637236&m=115128","img":"https://images.gotodirect.com/uploads/products/2025/3/67d238b5bd1b9.jpg","category":"","brand":"","in_stock":null,"partner":"advadv"},{"title":"HPE P67094-B21 | 2.2GHz LGA4677 Xeon Gold 5520+ 28-Core Processor","price":2725.92,"currency":"","url":"https://www.awin1.com/pclick.php?p=41622622836&a=2637236&m=115128","img":"https://images.gotodirect.com/uploads/products/2025/3/67d238b6df07b.jpg","category":"","brand":"","in_stock":null,"partner":"advadv"},{"title":"Dell 338-CBXS | 3.2GHz LGA4189 Intel Xeon Gold 5315Y 8-Core Processor","price":1837.05,"currency":"","url":"https://www.awin1.com/pclick.php?p=41622622835&a=2637236&m=115128","img":"https://images.gotodirect.com/uploads/products/2025/3/67d238b760626.jpg","category":"","brand":"","in_stock":null,"partner":"advadv"},{"title":"Dell PGGX1 | 2.20GHz LGA4189 Gold 5320 26-Core Processor","price":2237.76,"currency":"","url":"https://www.awin1.com/pclick.php?p=41622622831&a=2637236&m=115128","img":"https://images.gotodirect.com/uploads/products/2025/3/67d238b97766c.jpg","category":"","brand":"","in_stock":null,"partner":"advadv"},{"title":"Dell 1MF9H | 2.6GHz 60MB LGA4677 Xeon Gold 6442Y 24-Core Processor","price":4383.72,"currency":"","url":"https://www.awin1.com/pclick.php?p=41622622829&a=2637236&m=115128","img":"https://images.gotodirect.com/uploads/products/2025/3/67d238ba976f1.jpg","category":"","brand":"","in_stock":null,"partner":"advadv"},{"title":"Intel SRMGS | Xeon Silver 4410T 10-Core 2.7GHz 26.25MB Processor","price":893.2,"currency":"","url":"https://www.awin1.com/pclick.php?p=41622622827&a=2637236&m=115128","img":"https://images.gotodirect.com/uploads/products/2025/3/67d238bbae733.jpg","category":"","brand":"","in_stock":null,"partner":"advadv"},{"title":"Intel SRM9E | Xeon W7-2475x 20-Core 2.60GHz 37.5MB Processor","price":2664.82,"currency":"","url":"https://www.awin1.com/pclick.php?p=41622622826&a=2637236&m=115128","img":"https://images.gotodirect.com/uploads/products/2025/3/67d238bc4cd5f.jpg","category":"","brand":"","in_stock":null,"partner":"advadv"},{"title":"Intel SRN6V | Xeon Gold 6538N 32-Core 2.1GHz LGA4677 Processor","price":5019.84,"currency":"","url":"https://www.awin1.com/pclick.php?p=41622622824&a=2637236&m=115128","img":"https://images.gotodirect.com/uploads/products/2025/3/67d238bd5ed31.jpg","category":"","brand":"","in_stock":null,"partner":"advadv"},{"title":"HPE P12021-001 | 2.30GHz LGA3647 Gold 5218N 16-Core Processor","price":646.36,"currency":"","url":"https://www.awin1.com/pclick.php?p=41622622823&a=2637236&m=115128","img":"https://images.gotodirect.com/uploads/products/2025/3/67d238bdd2d1d.jpg","category":"","brand":"","in_stock":null,"partner":"advadv"},{"title":"HPE P67664-001 | 2.10GHz LGA4677 Xeon Gold 6538N 32-Core Processor","price":5019.84,"currency":"","url":"https://www.awin1.com/pclick.php?p=41622622819&a=2637236&m=115128","img":"https://images.gotodirect.com/uploads/products/2025/3/67d238c020d28.jpg","category":"","brand":"","in_stock":null,"partner":"advadv"},{"title":"Intel SRN6T | Xeon Gold 5512U 28-Core 2.10GHz LGA4677 Processor","price":1880.34,"currency":"","url":"https://www.awin1.com/pclick.php?p=41622622818&a=2637236&m=115128","img":"https://images.gotodirect.com/uploads/products/2025/3/67d238c0a8118.jpg","category":"","brand":"","in_stock":null,"partner":"advadv"},{"title":"Intel SRN6P | Xeon Gold 6542Y 24-Core 2.9GHz LGA4677 Processor","price":4334.04,"currency":"","url":"https://www.awin1.com/pclick.php?p=41622622816&a=2637236&m=115128","img":"https://images.gotodirect.com/uploads/products/2025/3/67d238c1c762e.jpg","category":"","brand":"","in_stock":null,"partner":"advadv"},{"title":"HPE P49656-B21 | 2.7GHz LGA4677 Xeon Silver 4410T 10-Core Processor","price":1013.61,"currency":"","url":"https://www.awin1.com/pclick.php?p=41622622815&a=2637236&m=115128","img":"https://images.gotodirect.com/uploads/products/2025/3/67d238c264577.jpg","category":"","brand":"","in_stock":null,"partner":"advadv"},{"title":"HPE P43447-B21 | 2GHz LGA4189 Intel Xeon Gold 6338 32-Core Processor","price":2893.32,"currency":"","url":"https://www.awin1.com/pclick.php?p=41622622810&a=2637236&m=115128","img":"https://images.gotodirect.com/uploads/products/2025/3/67d238c573741.jpg","category":"","brand":"","in_stock":null,"partner":"advadv"},{"title":"Dell 338-CBCI | 2.6GHz 42MB Intel Xeon Gold 6348 28-Core Processor","price":2938.73,"currency":"","url":"https://www.awin1.com/pclick.php?p=41622622806&a=2637236&m=115128","img":"https://images.gotodirect.com/uploads/products/2025/3/67d238c7b03af.jpg","category":"","brand":"","in_stock":null,"partner":"advadv"},{"title":"Dell XX1RD | 2.20GHz LGA4189 Platinum 8352Y 32-Core Processor","price":3021.84,"currency":"","url":"https://www.awin1.com/pclick.php?p=41622622802&a=2637236&m=115128","img":"https://images.gotodirect.com/uploads/products/2025/3/67d238ca00054.jpg","category":"","brand":"","in_stock":null,"partner":"advadv"},{"title":"HPE P58782-B21 | 2.5GHz 64MB L3 SKT SP5 EPYC 9224 24-Core Processor","price":2560.77,"currency":"","url":"https://www.awin1.com/pclick.php?p=41622622801&a=2637236&m=115128","img":"https://images.gotodirect.com/uploads/products/2025/3/67d238ca433bc.jpg","category":"","brand":"","in_stock":null,"partner":"advadv"},{"title":"Dell P5K13 | 2.4GHz 24MB Intel Xeon Silver 4314 16-Core Processor","price":1107.42,"currency":"","url":"https://www.awin1.com/pclick.php?p=41622622795&a=2637236&m=115128","img":"https://images.gotodirect.com/uploads/products/2025/3/67d238cde9293.jpg","category":"","brand":"","in_stock":null,"partner":"advadv"},{"title":"Dell M5H2H | 2.65GHz Socket SP6 EPYC 8324P 32-Core Processor","price":2794.18,"currency":"","url":"https://www.awin1.com/pclick.php?p=41622622791&a=2637236&m=115128","img":"https://images.gotodirect.com/uploads/products/2025/3/67d238d01c6d7.jpg","category":"","brand":"","in_stock":null,"partner":"advadv"},{"title":"HPE P67642-001 | 2.90GHz LGA4677 Xeon Gold 6542Y 24-Core Processor","price":4334.04,"currency":"","url":"https://www.awin1.com/pclick.php?p=41622622790&a=2637236&m=115128","img":"https://images.gotodirect.com/uploads/products/2025/3/67d238d0e6e79.jpg","category":"","brand":"","in_stock":null,"partner":"advadv"},{"title":"Intel SRMGK | Xeon Gold 6442y 24-Core 2.60GHz 60MB Processor","price":2527.96,"currency":"","url":"https://www.awin1.com/pclick.php?p=41622622789&a=2637236&m=115128","img":"https://images.gotodirect.com/uploads/products/2025/3/67d238d146a2a.jpg","category":"","brand":"","in_stock":null,"partner":"advadv"},{"title":"Dell 59R92 | 2.9GHz 22.5MB LGA4677 Xeon Gold 5415+ 8-Core Processor","price":1641.69,"currency":"","url":"https://www.awin1.com/pclick.php?p=41622622785&a=2637236&m=115128","img":"https://images.gotodirect.com/uploads/products/2025/3/67d238d3aa078.jpg","category":"","brand":"","in_stock":null,"partner":"advadv"},{"title":"HPE P43451-B21 | 3.10GHz 36MB Intel Xeon Gold 6346 16-Core Processor","price":2221.97,"currency":"","url":"https://www.awin1.com/pclick.php?p=41622622784&a=2637236&m=115128","img":"https://images.gotodirect.com/uploads/products/2025/3/67d238d419e55.jpg","category":"","brand":"","in_stock":null,"partner":"advadv"},{"title":"Intel SRN62 | Xeon Bronze 3508U 8-Core 2.10GHz LGA4677 Processor","price":642.43,"currency":"","url":"https://www.awin1.com/pclick.php?p=41622622779&a=2637236&m=115128","img":"https://images.gotodirect.com/uploads/products/2025/3/67d238d701a85.jpg","category":"","brand":"","in_stock":null,"partner":"advadv"},{"title":"HPE P67101-B21 | 2.10GHz LGA4677 Xeon Gold 5512U 28-Core Processor","price":1880.34,"currency":"","url":"https://www.awin1.com/pclick.php?p=41622622776&a=2637236&m=115128","img":"https://images.gotodirect.com/uploads/products/2025/3/67d238d862ffe.jpg","category":"","brand":"","in_stock":null,"partner":"advadv"},{"title":"Lite-On PS-2112-16D | 1100W Power Supply for PowerEdge R650","price":406.78,"currency":"","url":"https://www.awin1.com/pclick.php?p=41622622775&a=2637236&m=115128","img":"https://images.gotodirect.com/uploads/products/2025/3/67d238d929870.jpg","category":"","brand":"","in_stock":null,"partner":"advadv"},{"title":"Intel PK8072205499500 | Xeon Gold 5515+ 8-C 3.2GHz LGA4677 Processor","price":1697.19,"currency":"","url":"https://www.awin1.com/pclick.php?p=41622622774&a=2637236&m=115128","img":"https://images.gotodirect.com/uploads/products/2025/3/67d238d97c8a9.jpg","category":"","brand":"","in_stock":null,"partner":"advadv"},{"title":"Dell 338-CMSP | 2.90GHz LGA4189 Intel Xeon Gold 6326 16-Core Processor","price":1855.92,"currency":"","url":"https://www.awin1.com/pclick.php?p=41622622772&a=2637236&m=115128","img":"https://images.gotodirect.com/uploads/products/2025/3/67d238daa1076.jpg","category":"","brand":"","in_stock":null,"partner":"advadv"},{"title":"Intel SRM9D | Xeon W7-2495X 24-Core 2.50GHz 45MB Processor","price":3297.24,"currency":"","url":"https://www.awin1.com/pclick.php?p=41622622771&a=2637236&m=115128","img":"https://images.gotodirect.com/uploads/products/2025/3/67d238db4b452.jpg","category":"","brand":"","in_stock":null,"partner":"advadv"},{"title":"Intel SRMGN | Xeon Gold 6448Y 32-Core 2.10GHz 60MB Processor","price":4659.81,"currency":"","url":"https://www.awin1.com/pclick.php?p=41622622768&a=2637236&m=115128","img":"https://images.gotodirect.com/uploads/products/2025/3/67d238dcb7a0f.jpg","category":"","brand":"","in_stock":null,"partner":"advadv"},{"title":"HPE P67103-B21 | 2GHz LGA4677 Xeon Silver 4510T 12-Core Processor","price":1028.3,"currency":"","url":"https://www.awin1.com/pclick.php?p=41622622766&a=2637236&m=115128","img":"https://images.gotodirect.com/uploads/products/2025/3/67d238dde2e98.jpg","category":"","brand":"","in_stock":null,"partner":"advadv"},{"title":"Dell PPMDK | 2.4GHz 54MB Intel Xeon Platinum 8360Y 36-Core Processor","price":3294.1,"currency":"","url":"https://www.awin1.com/pclick.php?p=41622622765&a=2637236&m=115128","img":"https://images.gotodirect.com/uploads/products/2025/3/67d238dea66aa.jpg","category":"","brand":"","in_stock":null,"partner":"advadv"},{"title":"HPE P58633-001 | 2.5GHz 64MB L3 SKT SP5 EPYC 9224 24-Core Processor","price":2560.77,"currency":"","url":"https://www.awin1.com/pclick.php?p=41622622762&a=2637236&m=115128","img":"https://images.gotodirect.com/uploads/products/2025/3/67d238dfe7aef.jpg","category":"","brand":"","in_stock":null,"partner":"advadv"},{"title":"Dell 90PFJ | 2.20GHz LGA4189 Platinum 8352S 32-Core Processor","price":2765.88,"currency":"","url":"https://www.awin1.com/pclick.php?p=41622622761&a=2637236&m=115128","img":"https://images.gotodirect.com/uploads/products/2025/3/67d238e1087b1.jpg","category":"","brand":"","in_stock":null,"partner":"advadv"},{"title":"Dell 338-CHSX | 2.20GHz LGA4677 Xeon Gold 6454S 32-Core Processor","price":4769.28,"currency":"","url":"https://www.awin1.com/pclick.php?p=41622622760&a=2637236&m=115128","img":"https://images.gotodirect.com/uploads/products/2025/3/67d238e1145c8.jpg","category":"","brand":"","in_stock":null,"partner":"advadv"},{"title":"HPE P60441-001 | 2.7GHz LGA4677 Xeon Silver 4410T 10-Core Processor","price":873.28,"currency":"","url":"https://www.awin1.com/pclick.php?p=41622622759&a=2637236&m=115128","img":"https://images.gotodirect.com/uploads/products/2025/3/67d238e229416.jpg","category":"","brand":"","in_stock":null,"partner":"advadv"},{"title":"Dell 338-BVKY | 1.90GHz 11MB Xeon Bronze 3206r 8-Core Processor","price":334.24,"currency":"","url":"https://www.awin1.com/pclick.php?p=41622622758&a=2637236&m=115128","img":"https://images.gotodirect.com/uploads/products/2025/3/67d238e22a415.jpg","category":"","brand":"","in_stock":null,"partner":"advadv"},{"title":"Intel PK8072205499600 | Xeon Silver 4514Y 16-C 2GHz LGA4677 Processor","price":1227.66,"currency":"","url":"https://www.awin1.com/pclick.php?p=41622622757&a=2637236&m=115128","img":"https://images.gotodirect.com/uploads/products/2025/3/67d238e3425c3.jpg","category":"","brand":"","in_stock":null,"partner":"advadv"},{"title":"HP 879728-B21 | 1.7GHz LGA3647 Xeon Bronze 3104 6-Core Processor","price":115.57,"currency":"","url":"https://www.awin1.com/pclick.php?p=41622622756&a=2637236&m=115128","img":"https://images.gotodirect.com/uploads/products/2025/3/67d238e34821f.jpg","category":"","brand":"","in_stock":null,"partner":"advadv"},{"title":"Intel SRN63 | Xeon Silver 4510T 12-Core 2GHz 30MB LGA4677 Processor","price":1028.3,"currency":"","url":"https://www.awin1.com/pclick.php?p=41622622753&a=2637236&m=115128","img":"https://images.gotodirect.com/uploads/products/2025/3/67d238e59f0e7.jpg","category":"","brand":"","in_stock":null,"partner":"advadv"},{"title":"Intel SRMGM | Xeon Gold 6438Y+ 32-Core 2GHz LGA4677 Processor","price":4119.12,"currency":"","url":"https://www.awin1.com/pclick.php?p=41622622750&a=2637236&m=115128","img":"https://images.gotodirect.com/uploads/products/2025/3/67d238e6e907c.jpg","category":"","brand":"","in_stock":null,"partner":"advadv"},{"title":"Dell 338-CBXM | 2.20GHz LGA4189 Gold 5320 26-Core Processor","price":2237.76,"currency":"","url":"https://www.awin1.com/pclick.php?p=41622622746&a=2637236&m=115128","img":"https://images.gotodirect.com/uploads/products/2025/3/67d238e9263c7.jpg","category":"","brand":"","in_stock":null,"partner":"advadv"},{"title":"HPE P67656-001 | 2.1GHz LGA4677 Xeon Gold 6530 32-Core Processor","price":3219.48,"currency":"","url":"https://www.awin1.com/pclick.php?p=41622622745&a=2637236&m=115128","img":"https://images.gotodirect.com/uploads/products/2025/3/67d238ea0e5da.jpg","category":"","brand":"","in_stock":null,"partner":"advadv"},{"title":"Dell 4YW1K | 2.6GHz 42MB Intel Xeon Gold 6348 28-Core Processor","price":2938.73,"currency":"","url":"https://www.awin1.com/pclick.php?p=41622622742&a=2637236&m=115128","img":"https://images.gotodirect.com/uploads/products/2025/3/67d238eb8924f.jpg","category":"","brand":"","in_stock":null,"partner":"advadv"},{"title":"Dell HVFCR | 2.8GHz LGA4189 Xeon Silver 4309Y 8-Core Processor","price":906.26,"currency":"","url":"https://www.awin1.com/pclick.php?p=41622622740&a=2637236&m=115128","img":"https://images.gotodirect.com/uploads/products/2025/3/67d238ec87627.jpg","category":"","brand":"","in_stock":null,"partner":"advadv"},{"title":"HPE P39472-B21 | 2.3GHz 256MB EPYC 7643 48-Core Processor","price":3355.56,"currency":"","url":"https://www.awin1.com/pclick.php?p=41622622739&a=2637236&m=115128","img":"https://images.gotodirect.com/uploads/products/2025/3/67d238edcc546.jpg","category":"","brand":"","in_stock":null,"partner":"advadv"},{"title":"Intel PK8072205500401 | Xeon Gold 5512U 28-C 2.1GHz LGA4677 Processor","price":1880.34,"currency":"","url":"https://www.awin1.com/pclick.php?p=41622622738&a=2637236&m=115128","img":"https://images.gotodirect.com/uploads/products/2025/3/67d238ede37f6.jpg","category":"","brand":"","in_stock":null,"partner":"advadv"},{"title":"Intel PK8072205500100 | Xeon Gold 6542Y 24-C 2.9GHz LGA4677 Processor","price":4334.04,"currency":"","url":"https://www.awin1.com/pclick.php?p=41622622736&a=2637236&m=115128","img":"https://images.gotodirect.com/uploads/products/2025/3/67d238eef0193.jpg","category":"","brand":"","in_stock":null,"partner":"advadv"},{"title":"Intel SRN6L | Xeon Gold 5520+ 28-Core 2.20GHz LGA4677 Processor","price":2725.92,"currency":"","url":"https://www.awin1.com/pclick.php?p=41622622734&a=2637236&m=115128","img":"https://images.gotodirect.com/uploads/products/2025/3/67d238f00c2e6.jpg","category":"","brand":"","in_stock":null,"partner":"advadv"},{"title":"Intel SRMGU | Xeon Gold 6416H 18-Core 2.20GHz 45MB Processor","price":2264.4,"currency":"","url":"https://www.awin1.com/pclick.php?p=41622622732&a=2637236&m=115128","img":"https://images.gotodirect.com/uploads/products/2025/3/67d238f11e0ed.jpg","category":"","brand":"","in_stock":null,"partner":"advadv"},{"title":"Dell 4XT2Y | 3.2GHz LGA4189 Intel Xeon Gold 5315Y 8-Core Processor","price":1837.05,"currency":"","url":"https://www.awin1.com/pclick.php?p=41622622731&a=2637236&m=115128","img":"https://images.gotodirect.com/uploads/products/2025/3/67d238f224a79.jpg","category":"","brand":"","in_stock":null,"partner":"advadv"},{"title":"Intel SRMGB | Xeon Bronze 3408U 8-Core 1.8GHz 22.5MB Processor","price":672.35,"currency":"","url":"https://www.awin1.com/pclick.php?p=41622622728&a=2637236&m=115128","img":"https://images.gotodirect.com/uploads/products/2025/3/67d238f36358a.jpg","category":"","brand":"","in_stock":null,"partner":"advadv"},{"title":"Dell 338-CLWG | 2.90GHz LGA4677 Xeon Gold 5415+ 8-Core Processor","price":1641.69,"currency":"","url":"https://www.awin1.com/pclick.php?p=41622622727&a=2637236&m=115128","img":"https://images.gotodirect.com/uploads/products/2025/3/67d238f453863.jpg","category":"","brand":"","in_stock":null,"partner":"advadv"},{"title":"Intel PK8071305121101 | Xeon Gold 6416H 18-Core 2.20GHz 45MB Processor","price":2264.4,"currency":"","url":"https://www.awin1.com/pclick.php?p=41622622725&a=2637236&m=115128","img":"https://images.gotodirect.com/uploads/products/2025/3/67d238f56c529.jpg","category":"","brand":"","in_stock":null,"partner":"advadv"},{"title":"HPE P41714-001 | 3.10GHz 36MB Intel Xeon Gold 6346 16-Core Processor","price":2221.97,"currency":"","url":"https://www.awin1.com/pclick.php?p=41622622723&a=2637236&m=115128","img":"https://images.gotodirect.com/uploads/products/2025/3/67d238f6990f2.jpg","category":"","brand":"","in_stock":null,"partner":"advadv"},{"title":"HPE P24765-B21 | 2.2GHz 35.75MB Xeon Gold 5220r 24-Core Processor","price":1658.34,"currency":"","url":"https://www.awin1.com/pclick.php?p=41622622720&a=2637236&m=115128","img":"https://images.gotodirect.com/uploads/products/2025/3/67d238f7d65cf.jpg","category":"","brand":"","in_stock":null,"partner":"advadv"},{"title":"Intel SRN5C | Xeon Gold 6530 32-Core 2.10GHz LGA4677 Processor","price":3219.48,"currency":"","url":"https://www.awin1.com/pclick.php?p=41622622719&a=2637236&m=115128","img":"https://images.gotodirect.com/uploads/products/2025/3/67d238f8b633a.jpg","category":"","brand":"","in_stock":null,"partner":"advadv"},{"title":"Intel SRMGJ | Xeon Gold 5412U 24-Core 2.10GHz 45MB Processor","price":1684.39,"currency":"","url":"https://www.awin1.com/pclick.php?p=41622622717&a=2637236&m=115128","img":"https://images.gotodirect.com/uploads/products/2025/3/67d238f9eaaa8.jpg","category":"","brand":"","in_stock":null,"partner":"advadv"},{"title":"Intel PK8072205499800 | Xeon Gold 5520+ 28-C 2.2GHz LGA4677 Processor","price":2725.92,"currency":"","url":"https://www.awin1.com/pclick.php?p=41622622716&a=2637236&m=115128","img":"https://images.gotodirect.com/uploads/products/2025/3/67d238f9f0536.jpg","category":"","brand":"","in_stock":null,"partner":"advadv"},{"title":"HP JL372-61001 | 2750W 54 V Switching AC Power Supply for Aruba X382","price":919.73,"currency":"","url":"https://www.awin1.com/pclick.php?p=41622622711&a=2637236&m=115128","img":"https://images.gotodirect.com/uploads/products/2025/3/67d238fd45723.jpg","category":"","brand":"","in_stock":null,"partner":"advadv"},{"title":"Intel SRKJ3 | Xeon Platinum 8351N 36 Cores 2.40GHz LGA4189 Processor","price":1672.77,"currency":"","url":"https://www.awin1.com/pclick.php?p=41622622710&a=2637236&m=115128","img":"https://images.gotodirect.com/uploads/products/2025/3/67d238fd55961.jpg","category":"","brand":"","in_stock":null,"partner":"advadv"},{"title":"Dell PX6WV | Xeon Gold 2.80GHz Server CPU","price":3311.62,"currency":"","url":"https://www.awin1.com/pclick.php?p=41622622709&a=2637236&m=115128","img":"https://images.gotodirect.com/uploads/products/2025/3/67d238fe6d0af.jpg","category":"","brand":"","in_stock":null,"partner":"advadv"},{"title":"HPE P44439-001 | 2.80GHz 36MB Intel Xeon Gold 6342 24-Core Processor","price":2640.09,"currency":"","url":"https://www.awin1.com/pclick.php?p=41622622708&a=2637236&m=115128","img":"https://images.gotodirect.com/uploads/products/2025/3/67d238fe8c4cb.jpg","category":"","brand":"","in_stock":null,"partner":"advadv"},{"title":"Dell J16DD | Xeon Platinum 2.60GHz Server CPU","price":3003.95,"currency":"","url":"https://www.awin1.com/pclick.php?p=41622622707&a=2637236&m=115128","img":"https://images.gotodirect.com/uploads/products/2025/3/67d238ff7c468.jpg","category":"","brand":"","in_stock":null,"partner":"advadv"},{"title":"HPE P60435-001 | 2.0GHz 45MB Xeon Gold 5418y 24-Core Processor","price":2316.57,"currency":"","url":"https://www.awin1.com/pclick.php?p=41622622706&a=2637236&m=115128","img":"https://images.gotodirect.com/uploads/products/2025/3/67d238ffa9fdd.jpg","category":"","brand":"","in_stock":null,"partner":"advadv"},{"title":"Dell 987HY | Xeon Gold 3.20GHz Server CPU","price":1182.88,"currency":"","url":"https://www.awin1.com/pclick.php?p=41622622705&a=2637236&m=115128","img":"https://images.gotodirect.com/uploads/products/2025/3/67d239009843c.jpg","category":"","brand":"","in_stock":null,"partner":"advadv"},{"title":"Dell C170V | Xeon Silver 2.30GHz Server CPU","price":1182.88,"currency":"","url":"https://www.awin1.com/pclick.php?p=41622622704&a=2637236&m=115128","img":"https://images.gotodirect.com/uploads/products/2025/3/67d23900c11f5.jpg","category":"","brand":"","in_stock":null,"partner":"advadv"},{"title":"Dell 77MV6 | Xeon Platinum 2.60GHz Server CPU","price":3998.16,"currency":"","url":"https://www.awin1.com/pclick.php?p=41622622703&a=2637236&m=115128","img":"https://images.gotodirect.com/uploads/products/2025/3/67d23901be01a.jpg","category":"","brand":"","in_stock":null,"partner":"advadv"},{"title":"HPE P41728-001 | 2.20GHz LGA4189 Platinum 8352S 32-Core Processor","price":2765.88,"currency":"","url":"https://www.awin1.com/pclick.php?p=41622622700&a=2637236&m=115128","img":"https://images.gotodirect.com/uploads/products/2025/3/67d23903151d1.jpg","category":"","brand":"","in_stock":null,"partner":"advadv"},{"title":"Intel SRFQ0 | Xeon Gold 6240L Octadeca-Core 2.60 GHz LGA3647 Processor","price":1817.51,"currency":"","url":"https://www.awin1.com/pclick.php?p=41622622699&a=2637236&m=115128","img":"https://images.gotodirect.com/uploads/products/2025/3/67d2390422581.jpg","category":"","brand":"","in_stock":null,"partner":"advadv"},{"title":"Dell 338-CBCN | Xeon Platinum 2.60GHz Server CPU","price":3998.16,"currency":"","url":"https://www.awin1.com/pclick.php?p=41622622698&a=2637236&m=115128","img":"https://images.gotodirect.com/uploads/products/2025/3/67d23904282a6.jpg","category":"","brand":"","in_stock":null,"partner":"advadv"},{"title":"HPE P41717-001 | 2.60GHz 48MB L3 Xeon Platinum 8358 32-Core Processor","price":3998.16,"currency":"","url":"https://www.awin1.com/pclick.php?p=41622622697&a=2637236&m=115128","img":"https://images.gotodirect.com/uploads/products/2025/3/67d239051b6e2.jpg","category":"","brand":"","in_stock":null,"partner":"advadv"},{"title":"Dell 077MV6 | Xeon Platinum 2.60GHz Server CPU","price":3249.83,"currency":"","url":"https://www.awin1.com/pclick.php?p=41622622696&a=2637236&m=115128","img":"https://images.gotodirect.com/uploads/products/2025/3/67d2390530686.jpg","category":"","brand":"","in_stock":null,"partner":"advadv"},{"title":"Intel SRFD9 | Xeon Gold 5218N 16-Core 2.30GHz LGA3647 Processor","price":681.24,"currency":"","url":"https://www.awin1.com/pclick.php?p=41622622693&a=2637236&m=115128","img":"https://images.gotodirect.com/uploads/products/2025/3/67d239078cdec.jpg","category":"","brand":"","in_stock":null,"partner":"advadv"},{"title":"Dell 338-CBWM | 3.2GHz 11.2GT/s 12MB Xeon Gold 5315Y 8-Core Processor","price":1496.83,"currency":"","url":"https://www.awin1.com/pclick.php?p=41622622692&a=2637236&m=115128","img":"https://images.gotodirect.com/uploads/products/2025/3/67d239078ff51.jpg","category":"","brand":"","in_stock":null,"partner":"advadv"},{"title":"Dell 338-CBXO | Xeon Silver 2.30GHz Server CPU","price":1323.5,"currency":"","url":"https://www.awin1.com/pclick.php?p=41622622691&a=2637236&m=115128","img":"https://images.gotodirect.com/uploads/products/2025/3/67d23908a0566.jpg","category":"","brand":"","in_stock":null,"partner":"advadv"},{"title":"HPE P19269-B21 | 2.10GHz LGA3647 Gold 5218R 20-Core Processor","price":839.59,"currency":"","url":"https://www.awin1.com/pclick.php?p=41622622690&a=2637236&m=115128","img":"https://images.gotodirect.com/uploads/products/2025/3/67d23909a8e41.jpg","category":"","brand":"","in_stock":null,"partner":"advadv"},{"title":"Dell HYGP5 | 3.00GHz 39MB Cache Xeon Gold 6354 18-Core Processor","price":2902.89,"currency":"","url":"https://www.awin1.com/pclick.php?p=41622622688&a=2637236&m=115128","img":"https://images.gotodirect.com/uploads/products/2025/3/67d2390ab7737.jpg","category":"","brand":"","in_stock":null,"partner":"advadv"},{"title":"Dell PN0W1 | Xeon Silver 2.80GHz Server CPU","price":717.02,"currency":"","url":"https://www.awin1.com/pclick.php?p=41622622687&a=2637236&m=115128","img":"https://images.gotodirect.com/uploads/products/2025/3/67d2390ade08f.jpg","category":"","brand":"","in_stock":null,"partner":"advadv"},{"title":"Dell YOWT2 | 3.05GHz Socket SP3 EPYC 7373X 16-Core Processor","price":2144.52,"currency":"","url":"https://www.awin1.com/pclick.php?p=41622622686&a=2637236&m=115128","img":"https://images.gotodirect.com/uploads/products/2025/3/67d2390bc878a.jpg","category":"","brand":"","in_stock":null,"partner":"advadv"},{"title":"Dell 94JF3 | 2.20GHz LGA4189 Platinum 8352S 32-Core Processor","price":2765.88,"currency":"","url":"https://www.awin1.com/pclick.php?p=41622622685&a=2637236&m=115128","img":"https://images.gotodirect.com/uploads/products/2025/3/67d2390be52dd.jpg","category":"","brand":"","in_stock":null,"partner":"advadv"},{"title":"HPE P42915-B21 | 2.00GHz 42MB L3 Xeon Gold 6330 28-Core Processor","price":1624.67,"currency":"","url":"https://www.awin1.com/pclick.php?p=41622622684&a=2637236&m=115128","img":"https://images.gotodirect.com/uploads/products/2025/3/67d2390cdaca1.jpg","category":"","brand":"","in_stock":null,"partner":"advadv"},{"title":"HPE P36802-B21 | 2.00GHz 42MB L3 Xeon Gold 6330 28-Core Processor","price":1624.67,"currency":"","url":"https://www.awin1.com/pclick.php?p=41622622683&a=2637236&m=115128","img":"https://images.gotodirect.com/uploads/products/2025/3/67d2390d26b36.jpg","category":"","brand":"","in_stock":null,"partner":"advadv"},{"title":"HPE P60434-001 | 2.00GHz 37.5MB Xeon Silver 4416+ 20-Core Processor","price":1636.61,"currency":"","url":"https://www.awin1.com/pclick.php?p=41622622682&a=2637236&m=115128","img":"https://images.gotodirect.com/uploads/products/2025/3/67d2390e10c2a.jpg","category":"","brand":"","in_stock":null,"partner":"advadv"},{"title":"Dell 338-BZRP | EPYC 2.8GHz Server CPU","price":1641.69,"currency":"","url":"https://www.awin1.com/pclick.php?p=41622622681&a=2637236&m=115128","img":"https://images.gotodirect.com/uploads/products/2025/3/67d2390e42f7d.jpg","category":"","brand":"","in_stock":null,"partner":"advadv"},{"title":"Dell 0XF938 | 930W Power Supply for PowerEdge 2900","price":211.76,"currency":"","url":"https://www.awin1.com/pclick.php?p=41622622680&a=2637236&m=115128","img":"https://images.gotodirect.com/uploads/products/2025/3/67d2390f3c96d.jpg","category":"","brand":"","in_stock":null,"partner":"advadv"},{"title":"HP P45961-001 | 1.8TB SFF SAS NHS 10K 12G Hard Drive","price":750.32,"currency":"","url":"https://www.awin1.com/pclick.php?p=41622622679&a=2637236&m=115128","img":"https://images.gotodirect.com/uploads/products/2025/3/67d2390f519c5.jpg","category":"","brand":"","in_stock":null,"partner":"advadv"},{"title":"Dell 470VC | 2.00GHz 42MB L3 Xeon Gold 6330 28-Core Processor","price":1624.67,"currency":"","url":"https://www.awin1.com/pclick.php?p=41622622677&a=2637236&m=115128","img":"https://images.gotodirect.com/uploads/products/2025/3/67d23914ed57d.jpg","category":"","brand":"","in_stock":null,"partner":"advadv"},{"title":"EMC 005052220 | 800GB SAS 6GB/s 2.5-inch Solid State Drive for VNX","price":477.36,"currency":"","url":"https://www.awin1.com/pclick.php?p=41622622676&a=2637236&m=115128","img":"https://images.gotodirect.com/uploads/products/2025/3/67d239173b163.jpg","category":"","brand":"","in_stock":null,"partner":"advadv"},{"title":"HP P50794-B21 | 2.50GHz 37.5MB Intel Xeon Gold 6426y 16-Core Processor","price":2316.57,"currency":"","url":"https://www.awin1.com/pclick.php?p=41622622674&a=2637236&m=115128","img":"https://images.gotodirect.com/uploads/products/2025/3/67d2391994a3c.jpg","category":"","brand":"","in_stock":null,"partner":"advadv"},{"title":"Intel PK8071305122001 | Xeon Gold 6421N 32-Core 1.80GHz 60MB Processor","price":2468.0,"currency":"","url":"https://www.awin1.com/pclick.php?p=41622622673&a=2637236&m=115128","img":"https://images.gotodirect.com/uploads/products/2025/3/67d2391acb4c2.jpg","category":"","brand":"","in_stock":null,"partner":"advadv"},{"title":"EMC 005051587 | 800GB 3.5 inch 12GB/s SAS Solid State Drive","price":496.08,"currency":"","url":"https://www.awin1.com/pclick.php?p=41622622672&a=2637236&m=115128","img":"https://images.gotodirect.com/uploads/products/2025/3/67d2391e18d93.jpg","category":"","brand":"","in_stock":null,"partner":"advadv"},{"title":"EMC 005051723 | 1.6TB SAS 6GB/s 2.5-inch Solid State Drive","price":565.11,"currency":"","url":"https://www.awin1.com/pclick.php?p=41622622671&a=2637236&m=115128","img":"https://images.gotodirect.com/uploads/products/2025/3/67d2391e1d858.jpg","category":"","brand":"","in_stock":null,"partner":"advadv"},{"title":"Intel 1603-V3 | Xeon E5-1603V3 4-Core 2.80GHz LGA2011-3 Processor","price":46.72,"currency":"","url":"https://www.awin1.com/pclick.php?p=41622622670&a=2637236&m=115128","img":"https://images.gotodirect.com/uploads/products/2025/3/67d2391f2e6d7.jpg","category":"","brand":"","in_stock":null,"partner":"advadv"},{"title":"HPE P60452-001 | 2GHz 30MB LGA4677 Xeon Gold 5416S 16-Core Processor","price":1283.87,"currency":"","url":"https://www.awin1.com/pclick.php?p=41622622668&a=2637236&m=115128","img":"https://images.gotodirect.com/uploads/products/2025/3/67d239218fcb0.jpg","category":"","brand":"","in_stock":null,"partner":"advadv"},{"title":"HPE P50793-B21 | 2.9GHz 22.5MB Xeon Gold 5415+ 8-Core Processor","price":1624.67,"currency":"","url":"https://www.awin1.com/pclick.php?p=41622622666&a=2637236&m=115128","img":"https://images.gotodirect.com/uploads/products/2025/3/67d239240602a.jpg","category":"","brand":"","in_stock":null,"partner":"advadv"},{"title":"HPE P67093-B21 | 2.2GHz LGA4677 Xeon Silver 4516Y+ 24-Core Processor","price":3546.72,"currency":"","url":"https://www.awin1.com/pclick.php?p=41622622664&a=2637236&m=115128","img":"https://images.gotodirect.com/uploads/products/2025/3/67d239254ceb9.jpg","category":"","brand":"","in_stock":null,"partner":"advadv"},{"title":"Dell 0XN6RX | EPYC 2.8GHz Server CPU","price":1710.51,"currency":"","url":"https://www.awin1.com/pclick.php?p=41622622663&a=2637236&m=115128","img":"https://images.gotodirect.com/uploads/products/2025/3/67d239265d57a.jpg","category":"","brand":"","in_stock":null,"partner":"advadv"},{"title":"HP 726659-B21 | Intel Xeon 6-Core(6-Core) E5-2620v3 2.40GHz 15MB L3 Cache 8GT/s QPI Socket FCLGA2011-3 22nm 85w Processor","price":64.57,"currency":"","url":"https://www.awin1.com/pclick.php?p=41623025660&a=2637236&m=115128","img":"https://images.gotodirect.com/uploads/products/2023/3/6409f11ccd8ea.jpg","category":"","brand":"","in_stock":null,"partner":"advadv"},{"title":"Intel CM8071505024520 | Xeon E-2488 8-Core 3.20GHz LGA1700 Processor","price":873.17,"currency":"","url":"https://www.awin1.com/pclick.php?p=41622622662&a=2637236&m=115128","img":"https://images.gotodirect.com/uploads/products/2025/3/67d23929ee940.jpg","category":"","brand":"","in_stock":null,"partner":"advadv"},{"title":"Intel SRM7B | Xeon Gold 6454S 32-Core 2.20GHz LGA4677 Processor","price":2829.6,"currency":"","url":"https://www.awin1.com/pclick.php?p=41622622661&a=2637236&m=115128","img":"https://images.gotodirect.com/uploads/products/2025/3/67d2392aa7658.jpg","category":"","brand":"","in_stock":null,"partner":"advadv"},{"title":"HPE P02670-L21 | Xeon Platinum 2.90GHz Server CPU","price":3786.92,"currency":"","url":"https://www.awin1.com/pclick.php?p=41622622660&a=2637236&m=115128","img":"https://images.gotodirect.com/uploads/products/2025/3/67d2392ba1064.jpg","category":"","brand":"","in_stock":null,"partner":"advadv"},{"title":"Intel SRMX7 | Xeon E-2478 8-Core 2.80GHz LGA1700 Processor","price":1080.28,"currency":"","url":"https://www.awin1.com/pclick.php?p=41622622659&a=2637236&m=115128","img":"https://images.gotodirect.com/uploads/products/2025/3/67d2392c5f080.jpg","category":"","brand":"","in_stock":null,"partner":"advadv"},{"title":"Intel SRMXB | Xeon E-2436 6-Core 2.90GHz LGA1700 Processor","price":500.88,"currency":"","url":"https://www.awin1.com/pclick.php?p=41622622658&a=2637236&m=115128","img":"https://images.gotodirect.com/uploads/products/2025/3/67d2392d84c31.jpg","category":"","brand":"","in_stock":null,"partner":"advadv"},{"title":"HPE P07356-L21 | Xeon Platinum 2.90GHz Server CPU","price":978.58,"currency":"","url":"https://www.awin1.com/pclick.php?p=41622622656&a=2637236&m=115128","img":"https://images.gotodirect.com/uploads/products/2025/3/67d23930c7b80.jpg","category":"","brand":"","in_stock":null,"partner":"advadv"},{"title":"Intel SRM9F | Xeon W5-2465x 16-Core 3.10GHz 33.75MB Processor","price":1905.4,"currency":"","url":"https://www.awin1.com/pclick.php?p=41622622655&a=2637236&m=115128","img":"https://images.gotodirect.com/uploads/products/2025/3/67d2393285240.jpg","category":"","brand":"","in_stock":null,"partner":"advadv"},{"title":"Aruba JL085A#B2B | X371 250W 100-240V AC Hot-plug Redundant Power Supply for 3810 Switch Series","price":403.98,"currency":"","url":"https://www.awin1.com/pclick.php?p=41622622654&a=2637236&m=115128","img":"https://images.gotodirect.com/uploads/products/2025/3/67d239335e224.jpg","category":"","brand":"","in_stock":null,"partner":"advadv"},{"title":"Dell 0JCF90 | Xeon 3.10GHz Server CPU","price":164.16,"currency":"","url":"https://www.awin1.com/pclick.php?p=41622622653&a=2637236&m=115128","img":"https://images.gotodirect.com/uploads/products/2025/3/67d23933a2274.jpg","category":"","brand":"","in_stock":null,"partner":"advadv"},{"title":"Intel CM8071505024905 | Xeon E-2456 6-Core 3.30GHz LGA1700 CPU","price":542.88,"currency":"","url":"https://www.awin1.com/pclick.php?p=41622622652&a=2637236&m=115128","img":"https://images.gotodirect.com/uploads/products/2025/3/67d2393856b76.jpg","category":"","brand":"","in_stock":null,"partner":"advadv"},{"title":"Intel PK8071305502200 | Xeon w5-2545 12-Core 3.50GHz LGA4677 CPU","price":1329.53,"currency":"","url":"https://www.awin1.com/pclick.php?p=41622622651&a=2637236&m=115128","img":"https://images.gotodirect.com/uploads/products/2025/3/67d23938bdc61.jpg","category":"","brand":"","in_stock":null,"partner":"advadv"},{"title":"Intel PK8071305501600 | Xeon w5-3535X 20-Core 2.90GHz LGA4677 CPU","price":2319.9,"currency":"","url":"https://www.awin1.com/pclick.php?p=41622622650&a=2637236&m=115128","img":"https://images.gotodirect.com/uploads/products/2025/3/67d2393ad7725.jpg","category":"","brand":"","in_stock":null,"partner":"advadv"},{"title":"Lenovo 4XB7A13554 | 1TB 7200RPM SATA 6GB/s 3.5-inch Hard Drive","price":220.19,"currency":"","url":"https://www.awin1.com/pclick.php?p=41622622649&a=2637236&m=115128","img":"https://images.gotodirect.com/uploads/products/2025/3/67d2393b49b49.jpg","category":"","brand":"","in_stock":null,"partner":"advadv"},{"title":"Dell XN6RX | EPYC 2.8GHz Server CPU","price":1710.51,"currency":"","url":"https://www.awin1.com/pclick.php?p=41622622646&a=2637236&m=115128","img":"https://images.gotodirect.com/uploads/products/2025/3/67d2393e5c658.jpg","category":"","brand":"","in_stock":null,"partner":"advadv"},{"title":"Intel PK8071305502100 | Xeon w5-2555X 14-Core 3.30GHz LGA4677 CPU","price":1468.53,"currency":"","url":"https://www.awin1.com/pclick.php?p=41622622644&a=2637236&m=115128","img":"https://images.gotodirect.com/uploads/products/2025/3/67d239416fbc1.jpg","category":"","brand":"","in_stock":null,"partner":"advadv"},{"title":"Intel SRMGD | Xeon Gold 6434 8-Core 3.70GHz 22.5MB Processor","price":2779.62,"currency":"","url":"https://www.awin1.com/pclick.php?p=41622622642&a=2637236&m=115128","img":"https://images.gotodirect.com/uploads/products/2025/3/67d2394332f1c.jpg","category":"","brand":"","in_stock":null,"partner":"advadv"},{"title":"Dell C06J5 | 2.1GHz 18MB Intel Xeon Silver 4310 12-Core Processor","price":622.17,"currency":"","url":"https://www.awin1.com/pclick.php?p=41622622641&a=2637236&m=115128","img":"https://images.gotodirect.com/uploads/products/2025/3/67d23943e1c09.jpg","category":"","brand":"","in_stock":null,"partner":"advadv"},{"title":"Seasonic PRIME-PX-1600 | 1600W 100-240V 15-10A ATX Power Supply","price":705.1,"currency":"","url":"https://www.awin1.com/pclick.php?p=41622622640&a=2637236&m=115128","img":"https://images.gotodirect.com/uploads/products/2025/3/67d239447b180.jpg","category":"","brand":"","in_stock":null,"partner":"advadv"},{"title":"Dell WKWJK | 2.1GHz 60MB LGA4677 Xeon Gold 6430 32-Core Processor","price":2224.44,"currency":"","url":"https://www.awin1.com/pclick.php?p=41622622639&a=2637236&m=115128","img":"https://images.gotodirect.com/uploads/products/2025/3/67d23945084fc.jpg","category":"","brand":"","in_stock":null,"partner":"advadv"},{"title":"Dell X0CHN | 2.8GHz LGA4677 Xeon Platinum 8462Y+ 32-Core Processor","price":5014.44,"currency":"","url":"https://www.awin1.com/pclick.php?p=41622622637&a=2637236&m=115128","img":"https://images.gotodirect.com/uploads/products/2025/3/67d2394609760.jpg","category":"","brand":"","in_stock":null,"partner":"advadv"},{"title":"Dell VMTTD | QLogic 2690 16Gbps 1-Port Fiber Channel PCIe FH Host Bus Adapter","price":425.73,"currency":"","url":"https://www.awin1.com/pclick.php?p=41622622636&a=2637236&m=115128","img":"https://images.gotodirect.com/uploads/products/2025/3/67d2394680268.jpg","category":"","brand":"","in_stock":null,"partner":"advadv"},{"title":"HPE P44442-001 | 3.00GHz 18MB Xeon Gold 5317 12-Core Processor","price":1241.28,"currency":"","url":"https://www.awin1.com/pclick.php?p=41622622635&a=2637236&m=115128","img":"https://images.gotodirect.com/uploads/products/2025/3/67d2394719ec3.jpg","category":"","brand":"","in_stock":null,"partner":"advadv"},{"title":"Intel PK8071305126600 | Xeon W7-2495X 24-Core 2.50GHz 45MB Processor","price":2859.84,"currency":"","url":"https://www.awin1.com/pclick.php?p=41622622634&a=2637236&m=115128","img":"https://images.gotodirect.com/uploads/products/2025/3/67d23947845ad.jpg","category":"","brand":"","in_stock":null,"partner":"advadv"},{"title":"Intel SRMGV | Xeon Gold 6418H 24-Core 2.10GHz LGA4677 Processor","price":3058.2,"currency":"","url":"https://www.awin1.com/pclick.php?p=41622622633&a=2637236&m=115128","img":"https://images.gotodirect.com/uploads/products/2025/3/67d239482fd2b.jpg","category":"","brand":"","in_stock":null,"partner":"advadv"},{"title":"Intel PK8072205560000 | Xeon Gold 5512U 28-C 2.1GHz LGA4677 Processor","price":1478.54,"currency":"","url":"https://www.awin1.com/pclick.php?p=41622622632&a=2637236&m=115128","img":"https://images.gotodirect.com/uploads/products/2025/3/67d239488f079.jpg","category":"","brand":"","in_stock":null,"partner":"advadv"},{"title":"Intel SRN6A | Gold 6534 8-Core 3.90GHz 22.5MB LGA4677 Processor","price":3851.28,"currency":"","url":"https://www.awin1.com/pclick.php?p=41622622630&a=2637236&m=115128","img":"https://images.gotodirect.com/uploads/products/2025/3/67d2394a581c6.jpg","category":"","brand":"","in_stock":null,"partner":"advadv"},{"title":"Intel SRKYF | Xeon Gold 2.30GHz Server CPU","price":3500.09,"currency":"","url":"https://www.awin1.com/pclick.php?p=41622622628&a=2637236&m=115128","img":"https://images.gotodirect.com/uploads/products/2025/3/67d2394b693aa.jpg","category":"","brand":"","in_stock":null,"partner":"advadv"},{"title":"HPE P49613-B21 | 2GHz LGA4677 Intel Xeon Gold 5420+ 28-Core Processor","price":4840.56,"currency":"","url":"https://www.awin1.com/pclick.php?p=41622622627&a=2637236&m=115128","img":"https://images.gotodirect.com/uploads/products/2025/3/67d2394bcf563.jpg","category":"","brand":"","in_stock":null,"partner":"advadv"},{"title":"Intel PK8071305126800 | Xeon W7-2475x 20-Core 2.60GHz 37.5MB Processor","price":2571.63,"currency":"","url":"https://www.awin1.com/pclick.php?p=41622622626&a=2637236&m=115128","img":"https://images.gotodirect.com/uploads/products/2025/3/67d2394c77530.jpg","category":"","brand":"","in_stock":null,"partner":"advadv"},{"title":"Intel PK8071305120901 | Platinum 8462Y+ 32-C 2.8GHz LGA4677 Processor","price":5060.57,"currency":"","url":"https://www.awin1.com/pclick.php?p=41622622625&a=2637236&m=115128","img":"https://images.gotodirect.com/uploads/products/2025/3/67d2394cd44d6.jpg","category":"","brand":"","in_stock":null,"partner":"advadv"},{"title":"Intel PK8071305121202 | Xeon Gold 6418H 24-Core 2.1GHz 60MB Processor","price":2654.69,"currency":"","url":"https://www.awin1.com/pclick.php?p=41622622624&a=2637236&m=115128","img":"https://images.gotodirect.com/uploads/products/2025/3/67d2394dac725.jpg","category":"","brand":"","in_stock":null,"partner":"advadv"},{"title":"Intel SRN60 | Xeon Silver 4510 12-Core 2.4GHz 30MB LGA4677 Processor","price":1080.28,"currency":"","url":"https://www.awin1.com/pclick.php?p=41622622623&a=2637236&m=115128","img":"https://images.gotodirect.com/uploads/products/2025/3/67d2394e9da92.jpg","category":"","brand":"","in_stock":null,"partner":"advadv"},{"title":"HPE P07349-B21 | Xeon Gold 2.50GHz Server CPU","price":479.7,"currency":"","url":"https://www.awin1.com/pclick.php?p=41622622621&a=2637236&m=115128","img":"https://images.gotodirect.com/uploads/products/2025/3/67d2394fa611e.jpg","category":"","brand":"","in_stock":null,"partner":"advadv"},{"title":"HPE P44444-001 | 2.4GHz 36MB Intel Xeon Gold 6336Y 24-Core Processor","price":2206.68,"currency":"","url":"https://www.awin1.com/pclick.php?p=41622622620&a=2637236&m=115128","img":"https://images.gotodirect.com/uploads/products/2025/3/67d2395014804.jpg","category":"","brand":"","in_stock":null,"partner":"advadv"},{"title":"Intel PK8071305127000 | Xeon W5-2465x 16Core 3.10GHz 33.75MB Processor","price":1999.33,"currency":"","url":"https://www.awin1.com/pclick.php?p=41622622619&a=2637236&m=115128","img":"https://images.gotodirect.com/uploads/products/2025/3/67d23950abcb1.jpg","category":"","brand":"","in_stock":null,"partner":"advadv"},{"title":"Intel PK8071305081800 | Xeon w7-3455 24-Core 2.5GHz LGA4677 Processor","price":3265.92,"currency":"","url":"https://www.awin1.com/pclick.php?p=41622622618&a=2637236&m=115128","img":"https://images.gotodirect.com/uploads/products/2025/3/67d239512600e.jpg","category":"","brand":"","in_stock":null,"partner":"advadv"},{"title":"Intel PK8071305127400 | Xeon w5-2445 10-Core 3.1GHz LGA4677 Processor","price":1111.3,"currency":"","url":"https://www.awin1.com/pclick.php?p=41622622617&a=2637236&m=115128","img":"https://images.gotodirect.com/uploads/products/2025/3/67d23951bc5b6.jpg","category":"","brand":"","in_stock":null,"partner":"advadv"},{"title":"Intel PK8072205559800 | Xeon Gold 6544Y 16-C 3.6GHz LGA4677 Processor","price":3684.52,"currency":"","url":"https://www.awin1.com/pclick.php?p=41622622615&a=2637236&m=115128","img":"https://images.gotodirect.com/uploads/products/2025/3/67d23952d4066.jpg","category":"","brand":"","in_stock":null,"partner":"advadv"},{"title":"Intel PK8071305122101 | Xeon Gold 6438N 32-Core2.0GHz 60MB Processor","price":3959.52,"currency":"","url":"https://www.awin1.com/pclick.php?p=41622622613&a=2637236&m=115128","img":"https://images.gotodirect.com/uploads/products/2025/3/67d239548b68a.jpg","category":"","brand":"","in_stock":null,"partner":"advadv"},{"title":"Intel PK8071305118801 | Xeon Gold 6434 8-Core 3.70GHz 22.5MB Processor","price":3123.13,"currency":"","url":"https://www.awin1.com/pclick.php?p=41622622612&a=2637236&m=115128","img":"https://images.gotodirect.com/uploads/products/2025/3/67d23954bff01.jpg","category":"","brand":"","in_stock":null,"partner":"advadv"},{"title":"HPE P11290-B21 | 1500W 264V Front Cabling Power Supply Kit","price":480.77,"currency":"","url":"https://www.awin1.com/pclick.php?p=41622622611&a=2637236&m=115128","img":"https://images.gotodirect.com/uploads/products/2025/3/67d23955ecb13.jpg","category":"","brand":"","in_stock":null,"partner":"advadv"},{"title":"Intel PK8072205558900 | Platinum 8562Y+ 32-C 2.8GHz LGA4677 Processor","price":4500.84,"currency":"","url":"https://www.awin1.com/pclick.php?p=41622622609&a=2637236&m=115128","img":"https://images.gotodirect.com/uploads/products/2025/3/67d2395729d6f.jpg","category":"","brand":"","in_stock":null,"partner":"advadv"},{"title":"HPE P23685-001 | 2.8GHz 64MB EPYC 7282 16-Core Processor","price":367.38,"currency":"","url":"https://www.awin1.com/pclick.php?p=41622622607&a=2637236&m=115128","img":"https://images.gotodirect.com/uploads/products/2025/3/67d239582baa8.jpg","category":"","brand":"","in_stock":null,"partner":"advadv"},{"title":"Intel SRMGW | Xeon Gold 6448H 32-Core 2.40GHz LGA4677 Processor","price":3481.92,"currency":"","url":"https://www.awin1.com/pclick.php?p=41622622605&a=2637236&m=115128","img":"https://images.gotodirect.com/uploads/products/2025/3/67d23959379d0.jpg","category":"","brand":"","in_stock":null,"partner":"advadv"},{"title":"Intel PK8071305554500 | Xeon Bronze 3508U 8-C 2.1GHz LGA4677 Processor","price":601.41,"currency":"","url":"https://www.awin1.com/pclick.php?p=41622622604&a=2637236&m=115128","img":"https://images.gotodirect.com/uploads/products/2025/3/67d239596f82d.jpg","category":"","brand":"","in_stock":null,"partner":"advadv"},{"title":"Intel SRMGL | Xeon Gold 5420+ 28-Core 2.0GHz 52.5MB Processor","price":2118.99,"currency":"","url":"https://www.awin1.com/pclick.php?p=41622622601&a=2637236&m=115128","img":"https://images.gotodirect.com/uploads/products/2025/3/67d2395b8f3db.jpg","category":"","brand":"","in_stock":null,"partner":"advadv"},{"title":"Intel PK8072205559600 | Xeon Gold 6542Y 24-C 2.9GHz LGA4677 Processor","price":2986.5,"currency":"","url":"https://www.awin1.com/pclick.php?p=41622622600&a=2637236&m=115128","img":"https://images.gotodirect.com/uploads/products/2025/3/67d2395bcc741.jpg","category":"","brand":"","in_stock":null,"partner":"advadv"},{"title":"HPE P41711-001 | 2.00GHz 42MB L3 Xeon Gold 6330 28-Core Processor","price":1624.67,"currency":"","url":"https://www.awin1.com/pclick.php?p=41622622598&a=2637236&m=115128","img":"https://images.gotodirect.com/uploads/products/2025/3/67d2395ceeb4a.jpg","category":"","brand":"","in_stock":null,"partner":"advadv"},{"title":"Intel BX807132475X | Xeon W7-2475x 20-Core 2.60GHz 37.5MB Processor","price":2556.9,"currency":"","url":"https://www.awin1.com/pclick.php?p=41622622596&a=2637236&m=115128","img":"https://images.gotodirect.com/uploads/products/2025/3/67d2395e29f55.jpg","category":"","brand":"","in_stock":null,"partner":"advadv"},{"title":"Dell JMF11 | 2.2GHz 35.75MB Intel Xeon Gold 5220r 24-Core Processor","price":1531.8,"currency":"","url":"https://www.awin1.com/pclick.php?p=41622622595&a=2637236&m=115128","img":"https://images.gotodirect.com/uploads/products/2025/3/67d2395f52b54.jpg","category":"","brand":"","in_stock":null,"partner":"advadv"},{"title":"Crucial CT2000T500SSD5 | T500 Solid State Drive 2 TB PCIe 4.0 NVMe","price":349.32,"currency":"","url":"https://www.awin1.com/pclick.php?p=41622622593&a=2637236&m=115128","img":"https://images.gotodirect.com/uploads/products/2025/3/67d2396110032.jpg","category":"","brand":"","in_stock":null,"partner":"advadv"},{"title":"Intel BX807133508U | Xeon Bronze 3508U 8-Core 2.1GHz LGA4677 Processor","price":630.54,"currency":"","url":"https://www.awin1.com/pclick.php?p=41622622592&a=2637236&m=115128","img":"https://images.gotodirect.com/uploads/products/2025/3/67d2396185ee8.jpg","category":"","brand":"","in_stock":null,"partner":"advadv"},{"title":"Intel CD8069504384601 | Xeon Gold 5218N 16 Core 2.30GHz Processor","price":503.1,"currency":"","url":"https://www.awin1.com/pclick.php?p=41622622591&a=2637236&m=115128","img":"https://images.gotodirect.com/uploads/products/2025/3/67d23962939fd.jpg","category":"","brand":"","in_stock":null,"partner":"advadv"},{"title":"Dell J7DJN | 2.40GHz LGA4189 Xeon Gold 6336Y 24-Core Processor","price":2206.68,"currency":"","url":"https://www.awin1.com/pclick.php?p=41622622590&a=2637236&m=115128","img":"https://images.gotodirect.com/uploads/products/2025/3/67d23963b34a2.jpg","category":"","brand":"","in_stock":null,"partner":"advadv"},{"title":"Dell 5Y1HD | Front RAID Controller Tray Bracket for PowerEdge","price":191.76,"currency":"","url":"https://www.awin1.com/pclick.php?p=41622622588&a=2637236&m=115128","img":"https://images.gotodirect.com/uploads/products/2025/3/67d23964c3198.jpg","category":"","brand":"","in_stock":null,"partner":"advadv"},{"title":"Quantum TD91J477 | Atlas III 9.1GB 7200RPM Ultra2 Wide SCSI 80-Pin 1MB Cache 3.5-inch Hard Drive","price":195.33,"currency":"","url":"https://www.awin1.com/pclick.php?p=41622622587&a=2637236&m=115128","img":"https://images.gotodirect.com/uploads/products/2025/3/67d239658e7ee.jpg","category":"","brand":"","in_stock":null,"partner":"advadv"},{"title":"Dell 17W46 | 2.90GHz 24MB LGA4189 Xeon Gold 6326 16-Core Processor","price":1842.6,"currency":"","url":"https://www.awin1.com/pclick.php?p=41622622586&a=2637236&m=115128","img":"https://images.gotodirect.com/uploads/products/2025/3/67d23965ebec0.jpg","category":"","brand":"","in_stock":null,"partner":"advadv"},{"title":"Quantum TY09L101 | 9.1GB 10000RPM SCSI 160Mb/s 3.5-inch Hard Drive","price":568.15,"currency":"","url":"https://www.awin1.com/pclick.php?p=41622622585&a=2637236&m=115128","img":"https://images.gotodirect.com/uploads/products/2025/3/67d23966aaaeb.jpg","category":"","brand":"","in_stock":null,"partner":"advadv"},{"title":"Dell 2K01X | 3.00GHz 18MB Xeon Gold 5317 12-Core Processor","price":1241.28,"currency":"","url":"https://www.awin1.com/pclick.php?p=41622622584&a=2637236&m=115128","img":"https://images.gotodirect.com/uploads/products/2025/3/67d2396714233.jpg","category":"","brand":"","in_stock":null,"partner":"advadv"},{"title":"NCR 16684-03 | 73GB 15000RPM Fiber Channel 3.5-inch Hard Drive","price":156.97,"currency":"","url":"https://www.awin1.com/pclick.php?p=41622622583&a=2637236&m=115128","img":"https://images.gotodirect.com/uploads/products/2025/3/67d23967ce194.jpg","category":"","brand":"","in_stock":null,"partner":"advadv"},{"title":"Quantum 940-40-9404 | ProDrive 42MB 3600RPM SCSI 50-Pin 64KB Cache 3.5-inch Hard Drive","price":460.02,"currency":"","url":"https://www.awin1.com/pclick.php?p=41622622582&a=2637236&m=115128","img":"https://images.gotodirect.com/uploads/products/2025/3/67d239683476c.jpg","category":"","brand":"","in_stock":null,"partner":"advadv"},{"title":"HP FS0004-02-6K | 660MB SCSI 50-Pin 5.25-inch Hard Drive","price":262.6,"currency":"","url":"https://www.awin1.com/pclick.php?p=41622622581&a=2637236&m=115128","img":"https://images.gotodirect.com/uploads/products/2025/3/67d23968e38a1.jpg","category":"","brand":"","in_stock":null,"partner":"advadv"},{"title":"Western Digital WDS280 | 80MB 3600RPM SCSI 2.5-inch Hard Drive","price":68.09,"currency":"","url":"https://www.awin1.com/pclick.php?p=41622622580&a=2637236&m=115128","img":"https://images.gotodirect.com/uploads/products/2025/3/67d239694a0f5.jpg","category":"","brand":"","in_stock":null,"partner":"advadv"},{"title":"Dell 338-CBWN | 3.00GHz 18MB Xeon Gold 5317 12-Core Processor","price":1241.28,"currency":"","url":"https://www.awin1.com/pclick.php?p=41622622578&a=2637236&m=115128","img":"https://images.gotodirect.com/uploads/products/2025/3/67d2396a7624f.jpg","category":"","brand":"","in_stock":null,"partner":"advadv"},{"title":"Quantum 940-40-9404-3 | ProDrive 42MB 3600RPM SCSI 50-Pin 64KB Cache 3.5-inch Hard Drive","price":450.15,"currency":"","url":"https://www.awin1.com/pclick.php?p=41622622577&a=2637236&m=115128","img":"https://images.gotodirect.com/uploads/products/2025/3/67d2396b41e48.jpg","category":"","brand":"","in_stock":null,"partner":"advadv"},{"title":"Maxtor D20MSL0K | 73GB 10000RPM SCSI 320MB/s 3.5-inch Hard Drive","price":370.77,"currency":"","url":"https://www.awin1.com/pclick.php?p=41622622576&a=2637236&m=115128","img":"https://images.gotodirect.com/uploads/products/2025/3/67d2396ba900c.jpg","category":"","brand":"","in_stock":null,"partner":"advadv"},{"title":"Quantum HN45D011 | Atlas II 4.5GB 7200RPM Ultra Wide SCSI 68-Pin 512KB Cache 3.5-inch Hard Drive","price":568.15,"currency":"","url":"https://www.awin1.com/pclick.php?p=41622622575&a=2637236&m=115128","img":"https://images.gotodirect.com/uploads/products/2025/3/67d2396c6e34d.jpg","category":"","brand":"","in_stock":null,"partner":"advadv"},{"title":"Quantum VK45J012 | Viking 4.5GB 7200RPM Ultra Wide SCSI 80-Pin 512KB Cache 3.5-inch Hard Drive","price":236.96,"currency":"","url":"https://www.awin1.com/pclick.php?p=41622622574&a=2637236&m=115128","img":"https://images.gotodirect.com/uploads/products/2025/3/67d2396ce2594.jpg","category":"","brand":"","in_stock":null,"partner":"advadv"},{"title":"Quantum VK45W012 | Viking 4.5GB 7200RPM Ultra Wide SCSI 512KB Cache 68-Pin 3.5-inch Hard Drive","price":568.15,"currency":"","url":"https://www.awin1.com/pclick.php?p=41622622573&a=2637236&m=115128","img":"https://images.gotodirect.com/uploads/products/2025/3/67d2396d80e32.jpg","category":"","brand":"","in_stock":null,"partner":"advadv"},{"title":"Western Digital WDS-387 | 60MB SCSI 3.5-inch Hard Drive","price":310.39,"currency":"","url":"https://www.awin1.com/pclick.php?p=41622622572&a=2637236&m=115128","img":"https://images.gotodirect.com/uploads/products/2025/3/67d2396e9f21f.jpg","category":"","brand":"","in_stock":null,"partner":"advadv"},{"title":"Advantech SQF-S25M8-512G-SAC | SQFlash 830 512GB MLC SATA 2.5-inch Solid State Drive","price":270.72,"currency":"","url":"https://www.awin1.com/pclick.php?p=41622622570&a=2637236&m=115128","img":"https://images.gotodirect.com/uploads/products/2025/3/67d239706c6fc.jpg","category":"","brand":"","in_stock":null,"partner":"advadv"},{"title":"Dell 338-CKYZ | 2.1GHz LGA4677 Xeon Gold 6430 32-Core Processor","price":2224.44,"currency":"","url":"https://www.awin1.com/pclick.php?p=41622622569&a=2637236&m=115128","img":"https://images.gotodirect.com/uploads/products/2025/3/67d23970ab805.jpg","category":"","brand":"","in_stock":null,"partner":"advadv"},{"title":"Emacs AX2-5300FB-2S | 300W Power Supply for Server","price":219.48,"currency":"","url":"https://www.awin1.com/pclick.php?p=41622622567&a=2637236&m=115128","img":"https://images.gotodirect.com/uploads/products/2025/3/67d2397218094.jpg","category":"","brand":"","in_stock":null,"partner":"advadv"},{"title":"Quantum TN09L461 | 9.1GB 10000RPM SCSI 160Mb/s 3.5-inch Hard Drive","price":568.15,"currency":"","url":"https://www.awin1.com/pclick.php?p=41622622566&a=2637236&m=115128","img":"https://images.gotodirect.com/uploads/products/2025/3/67d23973210de.jpg","category":"","brand":"","in_stock":null,"partner":"advadv"},{"title":"Quantum 940-40-9400 | ProDrive 42MB 3600RPM SCSI 50-Pin 64KB Cache 3.5-inch Hard Drive","price":355.46,"currency":"","url":"https://www.awin1.com/pclick.php?p=41622622565&a=2637236&m=115128","img":"https://images.gotodirect.com/uploads/products/2025/3/67d239743bfc2.jpg","category":"","brand":"","in_stock":null,"partner":"advadv"},{"title":"EMC 005052459 | 7.68TB SAS 12GB/s 2.5-inch Enterprise Solid State Drive","price":1187.7,"currency":"","url":"https://www.awin1.com/pclick.php?p=41622622564&a=2637236&m=115128","img":"https://images.gotodirect.com/uploads/products/2025/3/67d239750aca5.jpg","category":"","brand":"","in_stock":null,"partner":"advadv"},{"title":"Western Digital WD740BLFS-01YBU0 | 74GB 10K RPM SATA 3GB/s 2.5-inch Hard Drive","price":355.2,"currency":"","url":"https://www.awin1.com/pclick.php?p=41622622563&a=2637236&m=115128","img":"https://images.gotodirect.com/uploads/products/2025/3/67d2397556509.jpg","category":"","brand":"","in_stock":null,"partner":"advadv"},{"title":"Maxtor 17G3137 | MXT Series 540MB 6300RPM Fast SCSI 50-Pin 256KB Cache 3.5-inch Hard Drive","price":383.12,"currency":"","url":"https://www.awin1.com/pclick.php?p=41622622562&a=2637236&m=115128","img":"https://images.gotodirect.com/uploads/products/2025/3/67d23976344a9.jpg","category":"","brand":"","in_stock":null,"partner":"advadv"},{"title":"Dell 338-CBXR | 3GHz 18MB LGA4189 Xeon Gold 5317 12-Core Processor","price":1697.19,"currency":"","url":"https://www.awin1.com/pclick.php?p=41622622561&a=2637236&m=115128","img":"https://images.gotodirect.com/uploads/products/2025/3/67d239766e1f6.jpg","category":"","brand":"","in_stock":null,"partner":"advadv"},{"title":"Maxtor 8D073J0025924 | 73.5GB 10000RPM SCSI 320MB/s 3.5-inch Hard Drive","price":132.14,"currency":"","url":"https://www.awin1.com/pclick.php?p=41622622560&a=2637236&m=115128","img":"https://images.gotodirect.com/uploads/products/2025/3/67d239775046f.jpg","category":"","brand":"","in_stock":null,"partner":"advadv"},{"title":"Dell 338-CBXU | 2.40GHz LGA4189 Xeon Gold 6336Y 24-Core Processor","price":2206.68,"currency":"","url":"https://www.awin1.com/pclick.php?p=41622622559&a=2637236&m=115128","img":"https://images.gotodirect.com/uploads/products/2025/3/67d23977785ef.jpg","category":"","brand":"","in_stock":null,"partner":"advadv"},{"title":"Sony 1-759-511-11 | 4.3GB 7200RPM Fast Wide SCSI 1MB Cache 50-Pin 3.5-inch Hard Drive","price":317.15,"currency":"","url":"https://www.awin1.com/pclick.php?p=41622622558&a=2637236&m=115128","img":"https://images.gotodirect.com/uploads/products/2025/3/67d2397866824.jpg","category":"","brand":"","in_stock":null,"partner":"advadv"},{"title":"Quantum 4550J | ATLAS II 4.5GB Ultra Wide SCSI 80-Pin 2.5-inch Hard Drive","price":109.22,"currency":"","url":"https://www.awin1.com/pclick.php?p=41622622557&a=2637236&m=115128","img":"https://images.gotodirect.com/uploads/products/2025/3/67d239789a196.jpg","category":"","brand":"","in_stock":null,"partner":"advadv"},{"title":"Quantum PX09W011 | Viking II 9.1GB 7200RPM Ultra Wide SCSI 68-Pin 512KB Cache 3.5-inch Hard Drive","price":568.15,"currency":"","url":"https://www.awin1.com/pclick.php?p=41622622556&a=2637236&m=115128","img":"https://images.gotodirect.com/uploads/products/2025/3/67d23979a037d.jpg","category":"","brand":"","in_stock":null,"partner":"advadv"},{"title":"Western Digital WDS-L42C2 | 40MB SCSI 50-Pin 3.5-inch Hard Drive","price":383.12,"currency":"","url":"https://www.awin1.com/pclick.php?p=41622622555&a=2637236&m=115128","img":"https://images.gotodirect.com/uploads/products/2025/3/67d23979c100f.jpg","category":"","brand":"","in_stock":null,"partner":"advadv"},{"title":"Dell 338-CBXJ | 2.90GHz 24MB Intel Xeon Gold 6326 16-Core Processor","price":1842.6,"currency":"","url":"https://www.awin1.com/pclick.php?p=41622622554&a=2637236&m=115128","img":"https://images.gotodirect.com/uploads/products/2025/3/67d2397ab9c57.jpg","category":"","brand":"","in_stock":null,"partner":"advadv"},{"title":"Quantum 4550S | Atlas II 4.5GB 7200RPM Ultra SCSI 50-Pin 512KB Cache 3.5-inch Hard Drive","price":355.46,"currency":"","url":"https://www.awin1.com/pclick.php?p=41622622552&a=2637236&m=115128","img":"https://images.gotodirect.com/uploads/products/2025/3/67d2397bcfc7c.jpg","category":"","brand":"","in_stock":null,"partner":"advadv"},{"title":"Quantum HN91W011 | 9.1GB 7200RPM Ultra Wide SCSI Single-Ended Narrow 68-Pin 3.5-inch Hard Drive","price":568.15,"currency":"","url":"https://www.awin1.com/pclick.php?p=41622622551&a=2637236&m=115128","img":"https://images.gotodirect.com/uploads/products/2025/3/67d2397bd1fe9.jpg","category":"","brand":"","in_stock":null,"partner":"advadv"},{"title":"Maxtor 8E073L0043462 | 73.5GB 15000RPM SCSI 320MB/s 3.5-inch Hard Drive","price":568.15,"currency":"","url":"https://www.awin1.com/pclick.php?p=41622622550&a=2637236&m=115128","img":"https://images.gotodirect.com/uploads/products/2025/3/67d2397d07dd9.jpg","category":"","brand":"","in_stock":null,"partner":"advadv"},{"title":"Maxtor 8E073L0-046662 | 73.5GB 15K RPM SCSI 320MB/s 3.5-inch Hard Drive","price":654.27,"currency":"","url":"https://www.awin1.com/pclick.php?p=41622622549&a=2637236&m=115128","img":"https://images.gotodirect.com/uploads/products/2025/3/67d2397d1062c.jpg","category":"","brand":"","in_stock":null,"partner":"advadv"},{"title":"Quantum 940-40-9404-4 | ProDrive 42MB 3600RPM SCSI 50-Pin 64KB Cache 3.5-inch Hard Drive","price":445.53,"currency":"","url":"https://www.awin1.com/pclick.php?p=41622622548&a=2637236&m=115128","img":"https://images.gotodirect.com/uploads/products/2025/3/67d2397e2f3d7.jpg","category":"","brand":"","in_stock":null,"partner":"advadv"},{"title":"Dell 338-BZYP | 3.00GHz Socket SP3 EPYC 7313P 16-Core Processor","price":680.26,"currency":"","url":"https://www.awin1.com/pclick.php?p=41622622547&a=2637236&m=115128","img":"https://images.gotodirect.com/uploads/products/2025/3/67d2397e31b11.jpg","category":"","brand":"","in_stock":null,"partner":"advadv"},{"title":"Dell 338-BVKT | 2.2GHz 35.75MB Intel Xeon Gold 5220r 24-Core Processor","price":1531.8,"currency":"","url":"https://www.awin1.com/pclick.php?p=41622622546&a=2637236&m=115128","img":"https://images.gotodirect.com/uploads/products/2025/3/67d2397f4bb48.jpg","category":"","brand":"","in_stock":null,"partner":"advadv"},{"title":"Maxtor XT-4380S | 380MB 5.25-inch 3600RPM Fast SCSI 50-Pin Internal Hard Drive","price":3241.15,"currency":"","url":"https://www.awin1.com/pclick.php?p=41622622545&a=2637236&m=115128","img":"https://images.gotodirect.com/uploads/products/2025/3/67d2397f4dcc4.jpg","category":"","brand":"","in_stock":null,"partner":"advadv"},{"title":"Dell 338-CBWI | 2.8GHz 12MB Intel Xeon Silver 4309Y 8-Core Processor","price":692.88,"currency":"","url":"https://www.awin1.com/pclick.php?p=41622622544&a=2637236&m=115128","img":"https://images.gotodirect.com/uploads/products/2025/3/67d2398057fad.jpg","category":"","brand":"","in_stock":null,"partner":"advadv"},{"title":"Maxtor 8D073J0-02495E | 73.5GB 10K RPM SCSI 320MB/s 3.5-inch Hard Drive","price":132.14,"currency":"","url":"https://www.awin1.com/pclick.php?p=41622622543&a=2637236&m=115128","img":"https://images.gotodirect.com/uploads/products/2025/3/67d2398070d57.jpg","category":"","brand":"","in_stock":null,"partner":"advadv"},{"title":"IBM ECF24464 | 9.1GB 10K UW SCSI 80-Pin Hot Swap 3.5-inch Hard Drive","price":302.51,"currency":"","url":"https://www.awin1.com/pclick.php?p=41622622542&a=2637236&m=115128","img":"https://images.gotodirect.com/uploads/products/2025/3/67d23981904d1.jpg","category":"","brand":"","in_stock":null,"partner":"advadv"},{"title":"Maxtor 8E073L004C252 | 73.5GB 15000RPM SCSI 320MB/s 3.5-inch Hard Drive","price":654.27,"currency":"","url":"https://www.awin1.com/pclick.php?p=41622622541&a=2637236&m=115128","img":"https://images.gotodirect.com/uploads/products/2025/3/67d23981c85f2.jpg","category":"","brand":"","in_stock":null,"partner":"advadv"},{"title":"Maxtor 8D073J0-025711 | 73.5GB 10K RPM SCSI 320MB/s 3.5-inch Hard Drive","price":383.12,"currency":"","url":"https://www.awin1.com/pclick.php?p=41622622540&a=2637236&m=115128","img":"https://images.gotodirect.com/uploads/products/2025/3/67d23982ac371.jpg","category":"","brand":"","in_stock":null,"partner":"advadv"},{"title":"Quantum LPS42S | ProDrive 42MB 3600RPM SCSI 50-Pin 64KB Cache 3.5-inch Hard Drive","price":170.66,"currency":"","url":"https://www.awin1.com/pclick.php?p=41622622539&a=2637236&m=115128","img":"https://images.gotodirect.com/uploads/products/2025/3/67d23983e6ff8.jpg","category":"","brand":"","in_stock":null,"partner":"advadv"},{"title":"IBM 40K1108 | 73GB 15000RPM SCSI 320MB/s 3.5-inch Hard Drive","price":286.73,"currency":"","url":"https://www.awin1.com/pclick.php?p=41622622538&a=2637236&m=115128","img":"https://images.gotodirect.com/uploads/products/2025/3/67d2398400826.jpg","category":"","brand":"","in_stock":null,"partner":"advadv"},{"title":"Maxtor 306-1081-00 | 73GB 10000RPM SCSI 320MB/s 3.5-inch Hard Drive","price":156.97,"currency":"","url":"https://www.awin1.com/pclick.php?p=41622622537&a=2637236&m=115128","img":"https://images.gotodirect.com/uploads/products/2025/3/67d23984ee274.jpg","category":"","brand":"","in_stock":null,"partner":"advadv"},{"title":"Samsung SHD-30560A | 560MB IDE/ATA-100 3.5-inch Hard Drive","price":214.52,"currency":"","url":"https://www.awin1.com/pclick.php?p=41622622536&a=2637236&m=115128","img":"https://images.gotodirect.com/uploads/products/2025/3/67d239850ad73.jpg","category":"","brand":"","in_stock":null,"partner":"advadv"},{"title":"Quantum 980-80-9402 | ProDrive 80MB 3600RPM SCSI 50-Pin 64KB Cache 3.5-inch Hard Drive","price":460.02,"currency":"","url":"https://www.awin1.com/pclick.php?p=41622622535&a=2637236&m=115128","img":"https://images.gotodirect.com/uploads/products/2025/3/67d2398617e8d.jpg","category":"","brand":"","in_stock":null,"partner":"advadv"},{"title":"Maxtor 8E073L0 | 73.5GB 15000RPM SCSI 320MB/s 3.5-inch Hard Drive","price":568.15,"currency":"","url":"https://www.awin1.com/pclick.php?p=41622622534&a=2637236&m=115128","img":"https://images.gotodirect.com/uploads/products/2025/3/67d239862d0f6.jpg","category":"","brand":"","in_stock":null,"partner":"advadv"},{"title":"Maxtor 8D073J0-02275E | 73.5GB 10K RPM SCSI 320MB/s 3.5-inch Hard Drive","price":183.42,"currency":"","url":"https://www.awin1.com/pclick.php?p=41622622533&a=2637236&m=115128","img":"https://images.gotodirect.com/uploads/products/2025/3/67d2398740326.jpg","category":"","brand":"","in_stock":null,"partner":"advadv"},{"title":"Dell 338-CBXL | 2.90GHz LGA4189 Intel Xeon Gold 6326 16-Core Processor","price":1842.6,"currency":"","url":"https://www.awin1.com/pclick.php?p=41622622532&a=2637236&m=115128","img":"https://images.gotodirect.com/uploads/products/2025/3/67d239884dddb.jpg","category":"","brand":"","in_stock":null,"partner":"advadv"},{"title":"Dell 3P6VG | 2.1GHz LGA4189 Xeon Silver 4310 12-Core Processor","price":472.64,"currency":"","url":"https://www.awin1.com/pclick.php?p=41622622531&a=2637236&m=115128","img":"https://images.gotodirect.com/uploads/products/2025/3/67d239895f3b6.jpg","category":"","brand":"","in_stock":null,"partner":"advadv"},{"title":"EMC 005052560 | 3.84TB SAS 12GB/s 2.5-inch Internal Solid State Drive","price":469.17,"currency":"","url":"https://www.awin1.com/pclick.php?p=41622622530&a=2637236&m=115128","img":"https://images.gotodirect.com/uploads/products/2025/3/67d239895f2bb.jpg","category":"","brand":"","in_stock":null,"partner":"advadv"},{"title":"IBM 42C0433 | 73.4GB 15000RPM SCSI 320MB/s 3.5-inch Hard Drive","price":286.73,"currency":"","url":"https://www.awin1.com/pclick.php?p=41622622529&a=2637236&m=115128","img":"https://images.gotodirect.com/uploads/products/2025/3/67d2398a73415.jpg","category":"","brand":"","in_stock":null,"partner":"advadv"},{"title":"Maxtor 8C073J008095G | 73.4GB 15000RPM SCSI 320MB/s 3.5-inch Hard Drive","price":183.42,"currency":"","url":"https://www.awin1.com/pclick.php?p=41622622528&a=2637236&m=115128","img":"https://images.gotodirect.com/uploads/products/2025/3/67d2398a8f93b.jpg","category":"","brand":"","in_stock":null,"partner":"advadv"},{"title":"Maxtor 8D073J002511 | 73.5GB 10000RPM SCSI 320MB/s 3.5-inch Hard Drive","price":132.14,"currency":"","url":"https://www.awin1.com/pclick.php?p=41622622527&a=2637236&m=115128","img":"https://images.gotodirect.com/uploads/products/2025/3/67d2398b7db2b.jpg","category":"","brand":"","in_stock":null,"partner":"advadv"},{"title":"Quantum 4300S | Grand Prix 4.3GB 7200RPM Ultra SCSI 512KB Cache 50-Pin 3.5-inch Hard Drive","price":542.72,"currency":"","url":"https://www.awin1.com/pclick.php?p=41622622526&a=2637236&m=115128","img":"https://images.gotodirect.com/uploads/products/2025/3/67d2398baace6.jpg","category":"","brand":"","in_stock":null,"partner":"advadv"},{"title":"Quantum VK22J881 | Viking 2.2GB 7200RPM Ultra Wide SCSI 80-Pin 512KB Cache 3.5-inch Hard Drive","price":278.85,"currency":"","url":"https://www.awin1.com/pclick.php?p=41622622525&a=2637236&m=115128","img":"https://images.gotodirect.com/uploads/products/2025/3/67d2398ccbab9.jpg","category":"","brand":"","in_stock":null,"partner":"advadv"},{"title":"Quantum PI16S011 | ProDrive ELS 170MB 3600RPM SCSI 50-Pin 32KB Cache 3.5-inch Hard Drive","price":294.63,"currency":"","url":"https://www.awin1.com/pclick.php?p=41622622524&a=2637236&m=115128","img":"https://images.gotodirect.com/uploads/products/2025/3/67d2398dc2f7a.jpg","category":"","brand":"","in_stock":null,"partner":"advadv"},{"title":"Seagate ST-2383E | 335MB 5.25 Hh SCSI Hard Drive","price":254.47,"currency":"","url":"https://www.awin1.com/pclick.php?p=41622622523&a=2637236&m=115128","img":"https://images.gotodirect.com/uploads/products/2025/3/67d2398df02dd.jpg","category":"","brand":"","in_stock":null,"partner":"advadv"},{"title":"Western Digital WDS-3160 | 160MB SCSI 3.5-inch Hard Drive","price":212.91,"currency":"","url":"https://www.awin1.com/pclick.php?p=41622622522&a=2637236&m=115128","img":"https://images.gotodirect.com/uploads/products/2025/3/67d2398ede4ca.jpg","category":"","brand":"","in_stock":null,"partner":"advadv"},{"title":"EMC 005050898 | 16GB mSATA 3GB/s Hot-Swappable 2.5-inch Hard Drive","price":97.79,"currency":"","url":"https://www.awin1.com/pclick.php?p=41622622521&a=2637236&m=115128","img":"https://images.gotodirect.com/uploads/products/2025/3/67d2398f07f3d.jpg","category":"","brand":"","in_stock":null,"partner":"advadv"},{"title":"Maxtor KU036J4 | 36.7GB 10000RPM SCSI 320MB/s 3.5-inch Hard Drive","price":117.98,"currency":"","url":"https://www.awin1.com/pclick.php?p=41622622520&a=2637236&m=115128","img":"https://images.gotodirect.com/uploads/products/2025/3/67d239901779a.jpg","category":"","brand":"","in_stock":null,"partner":"advadv"},{"title":"IBM 26K5640 | 36.7GB 15K RPM SAS 3GB/s 3.5-inch Hard Drive","price":119.13,"currency":"","url":"https://www.awin1.com/pclick.php?p=41622622519&a=2637236&m=115128","img":"https://images.gotodirect.com/uploads/products/2025/3/67d23990259eb.jpg","category":"","brand":"","in_stock":null,"partner":"advadv"},{"title":"Western Digital WD-3158 | 120MB SCSI 50-Pin 3.5-inch Hard Drive","price":404.82,"currency":"","url":"https://www.awin1.com/pclick.php?p=41622622518&a=2637236&m=115128","img":"https://images.gotodirect.com/uploads/products/2025/3/67d2399132384.jpg","category":"","brand":"","in_stock":null,"partner":"advadv"},{"title":"Maxtor 8E036J0-02C511 | 36.7GB 15K RPM SCSI 320MB/s 3.5-inch Hard Drive","price":117.98,"currency":"","url":"https://www.awin1.com/pclick.php?p=41622622517&a=2637236&m=115128","img":"https://images.gotodirect.com/uploads/products/2025/3/67d239914de5b.jpg","category":"","brand":"","in_stock":null,"partner":"advadv"},{"title":"Maxtor 8B036J00 | 36.7GB 10000RPM SCSI 320MB/s 3.5-inch Hard Drive","price":280.8,"currency":"","url":"https://www.awin1.com/pclick.php?p=41622622516&a=2637236&m=115128","img":"https://images.gotodirect.com/uploads/products/2025/3/67d2399265519.jpg","category":"","brand":"","in_stock":null,"partner":"advadv"}]